Workbook

Sheet UBS P. DO SOL
B1: UBS - Unidade Básica Paraíso do Sol
B3: ESTIMATIVA DE ENTREGA: | M3: RESTAM : | Q3: DIAS
B5: OBJETIVO
B6: Acompanhar, monitorar e controlar as etapas da execução da obra, bem como a aquisição de equipamentos necessários para seu pleno funcionamento. Problema: Risco de descompasso entre o término das obras e a aquisição de materiais e equipamentos. Solução: Implantar ferramenta única para organizar e acompanhar as aquisições por unidade, conforme o cronograma das obras. Benefício: Garantir início de funcionamento sem atrasos, com melhor planejamento e integração entre as áreas. | Q6: LEGENDA
Q8: 1 | S8: 1. Atenção | U8: Em processo de cotação
Q9: 2 | S9: 2. Em andamento | U9: Em processo de compra
Q10: 3 | S10: 3. Finalizado | U10: Entregue
Q11: 4 | S11: 4. Não Necessita
B14: QTDE | C14: ITENS | E14: Valor Unitário (Estimado) | G14: Valor Total (Estimado) | I14: FONTE DE COMPRA | K14: SD | M14: RC | O14: AF | Q14: CONTRAPARTIDA | S14: ENTREGA | U14: COMPLEMENTO
B16: 7 | C16: LONGARINA OTI PE METAL - 02 LUGARES | E16: 2602 | G16: =B16*E16 -> 18214 | I16: HUMANITAS | K16: 4 | M16: 4 | O16: 4 | Q16: 3 | S16: 3 | U16: Está contemplado no EXP. 23951/2026
B17: 7 | C17: LONGARINA OTI PE METAL - 03 LUGARES | E17: 3573 | G17: =B17*E17 -> 25011 | I17: HUMANITAS | K17: 4 | M17: 4 | O17: 4 | Q17: 3 | S17: 3 | U17: Está contemplado no EXP. 23951/2026
B18: 1 | C18: LONGARINA OTI PE METAL - POLATRONA PLUS | E18: 1920 | G18: =B18*E18 -> 1920 | I18: HUMANITAS | K18: 4 | M18: 4 | O18: 4 | Q18: 3 | S18: 3 | U18: Está contemplado no EXP. 23951/2026
B19: 1 | C19: CONTRATAÇÃO DE EMPRESA ESPECIALIZADA EM FORNECIMENTO E INSTALAÇÃO DE PLACAS E TOTENS DE IDENTIFICAÇÃO | E19: 24000 | G19: =B19*E19 -> 24000 | I19: PREFEITURA | K19: 3 | M19: 3 | O19: 2 | Q19: 2 | S19: 2 | U19: RC 3577/2026 - EXP.16007/2026 enviado ao DGOC em 11/03/2026 (canelado) - Segue SD 1777/2026 Verba Federal
C21: TOTAL | G21: =SUM(G16:G19) -> 69145
E23: HUMANITAS | G23: =SUMIF(I16:I19,E23,G16:G19) -> 45145
E25: PREFEITURA | G25: =SUMIF(I16:I19,E25,G16:G19) -> 24000
C26: Total | K26: =SUM(K27:K29) -> 1 | M26: =SUM(M27:M29) -> 1 | O26: =SUM(O27:O29) -> 1 | Q26: =SUM(Q27:Q30) -> 4 | S26: =SUM(S27:S30) -> 4
C27: Atenção | K27: =COUNTIF(K16:K19,Q8) -> 0 | M27: =COUNTIF(M16:M19,Q8) -> 0 | O27: =COUNTIF(O16:O19,Q8) -> 0 | Q27: =COUNTIF(Q16:Q19,Q8) -> 0 | S27: =COUNTIF(S16:S19,Q8) -> 0
C28: Em andamento | K28: =COUNTIF(K16:K19,Q9) -> 0 | M28: =COUNTIF(M16:M19,Q9) -> 0 | O28: =COUNTIF(O16:O19,Q9) -> 1 | Q28: =COUNTIF(Q16:Q19,Q9) -> 1 | S28: =COUNTIF(S16:S19,Q9) -> 1
C29: Finalizado | K29: =COUNTIF(H16:K19,Q10) -> 1 | M29: =COUNTIF(M16:M19,Q10) -> 1 | O29: =COUNTIF(O16:O19,Q10) -> 0 | Q29: =COUNTIF(Q16:Q19,Q10) -> 3 | S29: =COUNTIF(S16:S19,Q10) -> 3
C30: Não Necessita | K30: =COUNTIF(K16:K19,Q11) -> 3 | M30: =COUNTIF(K16:K19,Q11) -> 3 | O30: =COUNTIF(K16:K19,Q11) -> 3 | Q30: =COUNTIF(Q16:Q19,Q11) -> 0 | S30: =COUNTIF(Q16:Q19,Q11) -> 0
E32: ADITAMENTO | G32: =SUMIF(I16:I19,E32,G16:G19) -> 0 | K32: SD | M32: RC | O32: AF | Q32: CONTRAPARTIDA | S32: ENTREGA
C34: FINALIZADA | K34: =K29/K26 -> 1 | M34: =M29/M26 -> 1 | O34: =O29/O26 -> 0 | Q34: =Q29/Q26 -> 0.75 | S34: =S29/S26 -> 0.75
C36: EM ANDAMENTO | K36: =K28/K26 -> 0 | M36: =M28/M26 -> 0 | O36: =O28/O26 -> 1 | Q36: =Q28/Q26 -> 0.25 | S36: =S28/S26 -> 0.25
C38: ATENÇÃO | K38: =K27/K26 -> 0 | M38: =M27/M26 -> 0 | O38: =O27/O26 -> 0 | Q38: =Q27/Q26 -> 0 | S38: =S27/S26 -> 0
G41: =G23+G25 -> 69145

Sheet UBS JD GRANJA
B1: UBS - Unidade Básica Jardim da Granja
B3: ESTIMATIVA DE ENTREGA: | M3: RESTAM : | Q3: DIAS
B5: OBJETIVO
B6: Acompanhar, monitorar e controlar as etapas da execução da obra, bem como a aquisição de equipamentos necessários para seu pleno funcionamento. Problema: Risco de descompasso entre o término das obras e a aquisição de materiais e equipamentos. Solução: Implantar ferramenta única para organizar e acompanhar as aquisições por unidade, conforme o cronograma das obras. Benefício: Garantir início de funcionamento sem atrasos, com melhor planejamento e integração entre as áreas. | Q6: LEGENDA
Q8: 1 | S8: 1. Atenção | U8: Em processo de cotação
Q9: 2 | S9: 2. Em andamento | U9: Em processo de compra
Q10: 3 | S10: 3. Finalizado | U10: Entregue
Q11: 4 | S11: 4. Não Necessita
B14: QTDE | C14: ITENS | E14: Valor Unitário (Estimado) | G14: Valor Total (Estimado) | I14: FONTE DE COMPRA | K14: SD | M14: RC | O14: AF | Q14: CONTRAPARTIDA | S14: ENTREGA | U14: COMPLEMENTO
B16: 7 | C16: LONGARINA OTI PE METAL - 02 LUGARES | E16: 2602 | G16: =B16*E16 -> 18214 | I16: HUMANITAS | K16: 4 | M16: 4 | O16: 4 | Q16: 2 | S16: 2 | U16: Está contemplado no EXP. 23951/2026
B17: 7 | C17: LONGARINA OTI PE METAL - 03 LUGARES | E17: 3573 | G17: =B17*E17 -> 25011 | I17: HUMANITAS | K17: 4 | M17: 4 | O17: 4 | Q17: 2 | S17: 2 | U17: Está contemplado no EXP. 23951/2026
B18: 1 | C18: LONGARINA OTI PE METAL - POLATRONA PLUS | E18: 1920 | G18: =B18*E18 -> 1920 | I18: HUMANITAS | K18: 4 | M18: 4 | O18: 4 | Q18: 2 | S18: 2 | U18: Está contemplado no EXP. 23951/2026
C20: TOTAL | G20: =SUM(G16:G18) -> 45145
E22: HUMANITAS | G22: =SUMIF(I16:I18,E22,G16:G18) -> 45145
E24: PREFEITURA | G24: =SUMIF(I16:I18,E24,G16:G18) -> 0
C25: Total | K25: =SUM(K26:K29) -> 3 | M25: =SUM(M26:M29) -> 3 | O25: =SUM(O26:O29) -> 3 | Q25: =SUM(Q26:Q29) -> 3 | S25: =SUM(S26:S29) -> 3
C26: Atenção | K26: =COUNTIF(K16:K18,Q8) -> 0 | M26: =COUNTIF(M16:M18,Q8) -> 0 | O26: =COUNTIF(O16:O18,Q8) -> 0 | Q26: =COUNTIF(Q16:Q18,Q8) -> 0 | S26: =COUNTIF(S16:S18,Q8) -> 0
C27: Em andamento | K27: =COUNTIF(K16:K18,Q9) -> 0 | M27: =COUNTIF(M16:M18,Q9) -> 0 | O27: =COUNTIF(O16:O18,Q9) -> 0 | Q27: =COUNTIF(Q16:Q18,Q9) -> 3 | S27: =COUNTIF(S16:S18,Q9) -> 3
C28: Finalizado | K28: =COUNTIF(H16:K18,Q10) -> 0 | M28: =COUNTIF(M16:M18,Q10) -> 0 | O28: =COUNTIF(O16:O18,Q10) -> 0 | Q28: =COUNTIF(Q16:Q18,Q10) -> 0 | S28: =COUNTIF(S16:S18,Q10) -> 0
C29: Não Necessita | K29: =COUNTIF(K16:K18,Q11) -> 3 | M29: =COUNTIF(K16:K18,Q11) -> 3 | O29: =COUNTIF(O16:O18,Q11) -> 3 | Q29: =COUNTIF(Q16:Q18,Q11) -> 0 | S29: =COUNTIF(Q16:Q18,Q11) -> 0
E31: ADITAMENTO | G31: =SUMIF(I16:I18,E31,G16:G18) -> 0 | K31: SD | M31: RC | O31: AF | Q31: CONTRAPARTIDA | S31: ENTREGA
C33: FINALIZADA | K33: =K28/K25 -> 0 | M33: =M28/M25 -> 0 | O33: =O28/O25 -> 0 | Q33: =Q28/Q25 -> 0 | S33: =S28/S25 -> 0
C35: EM ANDAMENTO | K35: =K27/K25 -> 0 | M35: =M27/M25 -> 0 | O35: =O27/O25 -> 0 | Q35: =Q27/Q25 -> 1 | S35: =S27/S25 -> 1
C37: ATENÇÃO | K37: =K26/K25 -> 0 | M37: =M26/M25 -> 0 | O37: =O26/O25 -> 0 | Q37: =Q26/Q25 -> 0 | S37: =S26/S25 -> 0
G40: =G22+G24 -> 45145

Sheet UBS JD SATÉLITE
B1: UBS - Unidade Básica Jardim Satélite
B3: ESTIMATIVA DE ENTREGA: | M3: RESTAM : | Q3: DIAS
B5: OBJETIVO
B6: Acompanhar, monitorar e controlar as etapas da execução da obra, bem como a aquisição de equipamentos necessários para seu pleno funcionamento. Problema: Risco de descompasso entre o término das obras e a aquisição de materiais e equipamentos. Solução: Implantar ferramenta única para organizar e acompanhar as aquisições por unidade, conforme o cronograma das obras. Benefício: Garantir início de funcionamento sem atrasos, com melhor planejamento e integração entre as áreas. | Q6: LEGENDA
Q8: 1 | S8: 1. Atenção | U8: Em processo de cotação
Q9: 2 | S9: 2. Em andamento | U9: Em processo de compra
Q10: 3 | S10: 3. Finalizado | U10: Entregue
Q11: 4 | S11: 4. Não Necessita
B14: QTDE | C14: ITENS | E14: Valor Unitário (Estimado) | G14: Valor Total (Estimado) | I14: FONTE DE COMPRA | K14: SD | M14: RC | O14: AF | Q14: CONTRAPARTIDA | S14: ENTREGA | U14: COMPLEMENTO
B16: 7 | C16: LONGARINA OTI PE METAL - 02 LUGARES | E16: 2602 | G16: =B16*E16 -> 18214 | I16: HUMANITAS | K16: 4 | M16: 4 | O16: 4 | Q16: 2 | S16: 2 | U16: Está contemplado no EXP. 23951/2026
B17: 7 | C17: LONGARINA OTI PE METAL - 03 LUGARES | E17: 3573 | G17: =B17*E17 -> 25011 | I17: HUMANITAS | K17: 4 | M17: 4 | O17: 4 | Q17: 2 | S17: 2 | U17: Está contemplado no EXP. 23951/2026
B18: 1 | C18: LONGARINA OTI PE METAL - POLATRONA PLUS | E18: 1920 | G18: =B18*E18 -> 1920 | I18: HUMANITAS | K18: 4 | M18: 4 | O18: 4 | Q18: 2 | S18: 2 | U18: Está contemplado no EXP. 23951/2026
C20: TOTAL | G20: =SUM(G16:G18) -> 45145
E22: HUMANITAS | G22: =SUMIF(I16:I18,E22,G16:G18) -> 45145
E24: PREFEITURA | G24: =SUMIF(I16:I18,E24,G16:G18) -> 0
C25: Total | K25: =SUM(K26:K29) -> 3 | M25: =SUM(M26:M29) -> 3 | O25: =SUM(O26:O29) -> 3 | Q25: =SUM(Q26:Q29) -> 3 | S25: =SUM(S26:S29) -> 3
C26: Atenção | K26: =COUNTIF(K16:K18,Q8) -> 0 | M26: =COUNTIF(M16:M18,Q8) -> 0 | O26: =COUNTIF(O16:O18,Q8) -> 0 | Q26: =COUNTIF(Q16:Q18,Q8) -> 0 | S26: =COUNTIF(S16:S18,Q8) -> 0
C27: Em andamento | K27: =COUNTIF(K16:K18,Q9) -> 0 | M27: =COUNTIF(M16:M18,Q9) -> 0 | O27: =COUNTIF(O16:O18,Q9) -> 0 | Q27: =COUNTIF(Q16:Q18,Q9) -> 3 | S27: =COUNTIF(S16:S18,Q9) -> 3
C28: Finalizado | K28: =COUNTIF(H16:K18,Q10) -> 0 | M28: =COUNTIF(M16:M18,Q10) -> 0 | O28: =COUNTIF(O16:O18,Q10) -> 0 | Q28: =COUNTIF(Q16:Q18,Q10) -> 0 | S28: =COUNTIF(S16:S18,Q10) -> 0
C29: Não Necessita | K29: =COUNTIF(K16:K18,Q11) -> 3 | M29: =COUNTIF(K16:K18,Q11) -> 3 | O29: =COUNTIF(K16:K18,Q11) -> 3 | Q29: =COUNTIF(Q16:Q18,Q11) -> 0 | S29: =COUNTIF(Q16:Q18,Q11) -> 0
E31: ADITAMENTO | G31: =SUMIF(I16:I18,E31,G16:G18) -> 0 | K31: SD | M31: RC | O31: AF | Q31: CONTRAPARTIDA | S31: ENTREGA
C33: FINALIZADA | K33: =K28/K25 -> 0 | M33: =M28/M25 -> 0 | O33: =O28/O25 -> 0 | Q33: =Q28/Q25 -> 0 | S33: =S28/S25 -> 0
C35: EM ANDAMENTO | K35: =K27/K25 -> 0 | M35: =M27/M25 -> 0 | O35: =O27/O25 -> 0 | Q35: =Q27/Q25 -> 1 | S35: =S27/S25 -> 1
C37: ATENÇÃO | K37: =K26/K25 -> 0 | M37: =M26/M25 -> 0 | O37: =O26/O25 -> 0 | Q37: =Q26/Q25 -> 0 | S37: =S26/S25 -> 0
G40: =G22+G24 -> 45145

Sheet UBS VL NAIR
B1: UBS - Unidade Básica Vila Nair
B3: ESTIMATIVA DE ENTREGA: | M3: RESTAM : | Q3: DIAS
B5: OBJETIVO
B6: Acompanhar, monitorar e controlar as etapas da execução da obra, bem como a aquisição de equipamentos necessários para seu pleno funcionamento. Problema: Risco de descompasso entre o término das obras e a aquisição de materiais e equipamentos. Solução: Implantar ferramenta única para organizar e acompanhar as aquisições por unidade, conforme o cronograma das obras. Benefício: Garantir início de funcionamento sem atrasos, com melhor planejamento e integração entre as áreas. | Q6: LEGENDA
Q8: 1 | S8: 1. Atenção | U8: Em processo de cotação
Q9: 2 | S9: 2. Em andamento | U9: Em processo de compra
Q10: 3 | S10: 3. Finalizado | U10: Entregue
Q11: 4 | S11: 4. Não Necessita
B14: QTDE | C14: ITENS | E14: Valor Unitário (Estimado) | G14: Valor Total (Estimado) | I14: FONTE DE COMPRA | K14: SD | M14: RC | O14: AF | Q14: CONTRAPARTIDA | S14: ENTREGA | U14: COMPLEMENTO
B16: 4 | C16: LONGARINA OTI PE METAL - 02 LUGARES | E16: 2602 | G16: =B16*E16 -> 10408 | I16: HUMANITAS | K16: 4 | M16: 4 | O16: 4 | Q16: 3 | S16: 3 | U16: Está contemplado no EXP. 23951/2026
B17: 4 | C17: LONGARINA OTI PE METAL - 03 LUGARES | E17: 3573 | G17: =B17*E17 -> 14292 | I17: HUMANITAS | K17: 4 | M17: 4 | O17: 4 | Q17: 3 | S17: 3 | U17: Está contemplado no EXP. 23951/2026
B18: 1 | C18: LONGARINA OTI PE METAL - POLATRONA PLUS | E18: 1920 | G18: =B18*E18 -> 1920 | I18: HUMANITAS | K18: 4 | M18: 4 | O18: 4 | Q18: 3 | S18: 3 | U18: Está contemplado no EXP. 23951/2026
C20: TOTAL | G20: =SUM(G16:G18) -> 26620
E22: HUMANITAS | G22: =SUMIF(I16:I18,E22,G16:G18) -> 26620
E24: PREFEITURA | G24: =SUMIF(I16:I18,E24,G16:G18) -> 0
C25: Total | K25: =SUM(K26:K29) -> 3 | M25: =SUM(M26:M29) -> 3 | O25: =SUM(O26:O29) -> 3 | Q25: =SUM(Q26:Q29) -> 3 | S25: =SUM(S26:S29) -> 3
C26: Atenção | K26: =COUNTIF(K16:K18,Q8) -> 0 | M26: =COUNTIF(M16:M18,Q8) -> 0 | O26: =COUNTIF(O16:O18,Q8) -> 0 | Q26: =COUNTIF(Q16:Q18,Q8) -> 0 | S26: =COUNTIF(S16:S18,Q8) -> 0
C27: Em andamento | K27: =COUNTIF(K16:K18,Q9) -> 0 | M27: =COUNTIF(M16:M18,Q9) -> 0 | O27: =COUNTIF(O16:O18,Q9) -> 0 | Q27: =COUNTIF(Q16:Q18,Q9) -> 0 | S27: =COUNTIF(S16:S18,Q9) -> 0
C28: Finalizado | K28: =COUNTIF(H16:K18,Q10) -> 0 | M28: =COUNTIF(M16:M18,Q10) -> 0 | O28: =COUNTIF(O16:O18,Q10) -> 0 | Q28: =COUNTIF(Q16:Q18,Q10) -> 3 | S28: =COUNTIF(S16:S18,Q10) -> 3
C29: Não Necessita | K29: =COUNTIF(K16:K18,Q11) -> 3 | M29: =COUNTIF(K16:K18,Q11) -> 3 | O29: =COUNTIF(K16:K18,Q11) -> 3 | Q29: =COUNTIF(Q16:Q18,Q11) -> 0 | S29: =COUNTIF(Q16:Q18,Q11) -> 0
E31: ADITAMENTO | G31: =SUMIF(I16:I18,E31,G16:G18) -> 0 | K31: SD | M31: RC | O31: AF | Q31: CONTRAPARTIDA | S31: ENTREGA
C33: FINALIZADA | K33: =K28/K25 -> 0 | M33: =M28/M25 -> 0 | O33: =O28/O25 -> 0 | Q33: =Q28/Q25 -> 1 | S33: =S28/S25 -> 1
C35: EM ANDAMENTO | K35: =K27/K25 -> 0 | M35: =M27/M25 -> 0 | O35: =O27/O25 -> 0 | Q35: =Q27/Q25 -> 0 | S35: =S27/S25 -> 0
C37: ATENÇÃO | K37: =K26/K25 -> 0 | M37: =M26/M25 -> 0 | O37: =O26/O25 -> 0 | Q37: =Q26/Q25 -> 0 | S37: =S26/S25 -> 0
G40: =G22+G24 -> 26620

Sheet UBS CAJURU
B1: UBS - Unidade Básica de Saúde Cajuru
B3: ESTIMATIVA DE ENTREGA: | K3: 46181 | M3: RESTAM : | O3: =K3-TODAY() -> -9 | Q3: DIAS
B5: OBJETIVO
B6: Acompanhar, monitorar e controlar as etapas da execução da obra, bem como a aquisição de equipamentos necessários para seu pleno funcionamento. Problema: Risco de descompasso entre o término das obras e a aquisição de materiais e equipamentos. Solução: Implantar ferramenta única para organizar e acompanhar as aquisições por unidade, conforme o cronograma das obras. Benefício: Garantir início de funcionamento sem atrasos, com melhor planejamento e integração entre as áreas. | Q6: LEGENDA
Q8: 1 | S8: 1. Atenção | U8: Em processo de cotação
Q9: 2 | S9: 2. Em andamento | U9: Em processo de compra
Q10: 3 | S10: 3. Finalizado | U10: Entregue
G11: ******** | I11: representa valor atualizado pelo Mapa de Preço | Q11: 4 | S11: 4. Não Necessita
B14: QTDE | C14: ITENS | E14: Valor Unitário (Estimado) | G14: Valor Total (Estimado) | I14: FONTE DE COMPRA | K14: SD | M14: RC | O14: AF | Q14: CONTRAPARTIDA | S14: ENTREGA | U14: COMPLEMENTO
B16: 1 | C16: APARELHO DE RX ODONTOLOGICO / ODONTOLÓGICO | E16: 9250 | G16: =B16*E16 -> 9250 | I16: HUMANITAS | K16: 4 | M16: 4 | O16: 4 | Q16: 2 | S16: 2 | U16: EXPEDIENTE 39664/2026 enviado ao Sr Otavio dia 01/06/2026. Enviado ao DPSS para cotação no dia 16/03/2026
B17: 2 | C17: APARELHO DE ULTRASSOM / ODONTOLOGICO | E17: 2574.05 | G17: =B17*E17 -> 5148.1 | I17: HUMANITAS | K17: 4 | M17: 4 | O17: 4 | Q17: 2 | S17: 2 | U17: EXPEDIENTE 35449/2026 enviado ao Sr Otavio no dia 18/05/2026. Enviado ao DPSS para cotação no dia 16/03/2026
B18: 4 | C18: ARMÁRIO VESTUÁRIO - M / F | E18: 1020 | G18: =B18*E18 -> 4080 | I18: HUMANITAS | K18: 4 | M18: 4 | O18: 4 | Q18: 2 | S18: 2 | U18: EXPEDIENTE 34459/2026 enviado ao Sr Otavio dia 14/05/2026. Enviado ao DPSS para cotação no dia 16/03/2026
B19: 1 | C19: ARMÁRIO VITRINE - 02 PORTAS | E19: 1378 | G19: =B19*E19 -> 1378 | I19: HUMANITAS | K19: 4 | M19: 4 | O19: 4 | Q19: 2 | S19: 2 | U19: EXPEDIENTE 39664/2026 enviado ao Sr Otavio dia 01/06/2026. Enviado ao DPSS para cotação no dia 16/03/2026
B20: 1 | C20: AUTOCLAVE 54 LITROS | E20: 25263.28 | G20: =B20*E20 -> 25263.28 | I20: HUMANITAS | K20: 4 | M20: 4 | O20: 4 | Q20: 2 | S20: 2 | U20: EXPEDIENTE 35449/2026 enviado ao Sr Otavio no dia 18/05/2026. Enviado ao DPSS para cotação no dia 16/03/2026
B21: 1 | C21: AVENTAL DE CHUMBO ADULTO - ODONTO | E21: 901.58 | G21: =B21*E21 -> 901.58 | I21: HUMANITAS | K21: 4 | M21: 4 | O21: 4 | Q21: 2 | S21: 2 | U21: EXPEDIENTE 35449/2026 enviado ao Sr Otavio no dia 18/05/2026. Enviado ao DPSS para cotação no dia 16/03/2026
B22: 1 | C22: AVENTAL DE CHUMBO INFANTIL - ODONTO | E22: 501.05 | G22: =B22*E22 -> 501.05 | I22: HUMANITAS | K22: 4 | M22: 4 | O22: 4 | Q22: 2 | S22: 2 | U22: EXPEDIENTE 39664/2026 enviado ao Sr Otavio dia 01/06/2026. Enviado ao DPSS para cotação no dia 16/03/2026
B23: 9 | C23: BALANÇA ADULTO DIGITAL | E23: 1714.65 | G23: =B23*E23 -> 15431.85 | I23: HUMANITAS | K23: 4 | M23: 4 | O23: 4 | Q23: 2 | S23: 2 | U23: EXPEDIENTE 39664/2026 enviado ao Sr Otavio dia 01/06/2026. Enviado ao DPSS para cotação no dia 16/03/2026
B24: 8 | C24: BALANÇA INFANTIL | E24: 990 | G24: =B24*E24 -> 7920 | I24: HUMANITAS | K24: 4 | M24: 4 | O24: 4 | Q24: 2 | S24: 2 | U24: EXPEDIENTE 35449/2026 enviado ao Sr Otavio no dia 18/05/2026. Enviado ao DPSS para cotação no dia 16/03/2026
B25: 1 | C25: BOMBONA - ODONTO | E25: 124.9 | G25: =B25*E25 -> 124.9 | I25: HUMANITAS | K25: 4 | M25: 4 | O25: 4 | Q25: 2 | S25: 2 | U25: EXPEDIENTE 39664/2026 enviado ao Sr Otavio dia 01/06/2026. Enviado ao DPSS para cotação no dia 16/03/2026
B26: 1 | C26: BRAÇADEIRA - INOX | E26: 147.9 | G26: =B26*E26 -> 147.9 | I26: HUMANITAS | K26: 4 | M26: 4 | O26: 4 | Q26: 2 | S26: 2 | U26: EXPEDIENTE 39664/2026 enviado ao Sr Otavio dia 01/06/2026. Enviado ao DPSS para cotação no dia 16/03/2026
B27: 2 | C27: CADEIRA DE COLETA | E27: 563.2 | G27: =B27*E27 -> 1126.4 | I27: HUMANITAS | K27: 4 | M27: 4 | O27: 4 | Q27: 2 | S27: 2 | U27: EXPEDIENTE 39664/2026 enviado ao Sr Otavio dia 01/06/2026. Enviado ao DPSS para cotação no dia 16/03/2026
... B79: 1 | C79: AR CONDICIONADO - VÁRIOS PARA COMPLEMENTAR NECESSIDADE | E79: 37355.75 | G79: =B79*E79 -> 37355.75 | I79: HUMANITAS | K79: 4 | M79: 4 | O79: 4 | Q79: 2 | S79: 2 | U79: EXPEDIENTE 34852/2026 enviado ao Sr Otavio na data 15/05/2026
C81: TOTAL | G81: =SUM(G16:G79) -> 533443.59
E83: HUMANITAS | G83: =SUMIF(I16:I79,E83,G16:G79) -> 533443.59
E85: PREFEITURA | G85: =SUMIF(I16:I79,E85,G16:G79) -> 0
C86: Total | K86: =SUM(K87:K90) -> 64 | M86: =SUM(M87:M90) -> 64 | O86: =SUM(O87:O90) -> 64 | Q86: =SUM(Q87:Q90) -> 64 | S86: =SUM(S87:S90) -> 64
C87: Atenção | K87: =COUNTIF(K16:K79,Q8) -> 0 | M87: =COUNTIF(M16:M79,Q8) -> 0 | O87: =COUNTIF(O16:O79,Q8) -> 0 | Q87: =COUNTIF(Q16:Q79,Q8) -> 0 | S87: =COUNTIF(S16:S79,Q8) -> 0
C88: Em andamento | K88: =COUNTIF(K16:K79,Q9) -> 0 | M88: =COUNTIF(M16:M79,Q9) -> 0 | O88: =COUNTIF(O16:O79,Q9) -> 0 | Q88: =COUNTIF(Q16:Q79,Q9) -> 64 | S88: =COUNTIF(S16:S79,Q9) -> 64
C89: Finalizado | K89: =COUNTIF(H16:K79,Q10) -> 0 | M89: =COUNTIF(M16:M79,Q10) -> 0 | O89: =COUNTIF(O16:O79,Q10) -> 0 | Q89: =COUNTIF(Q16:Q79,Q10) -> 0 | S89: =COUNTIF(S16:S79,Q10) -> 0
C90: Não Necessita | K90: =COUNTIF(K16:K79,Q11) -> 64 | M90: =COUNTIF(K16:K79,Q11) -> 64 | O90: =COUNTIF(O16:O79,Q11) -> 64 | Q90: =COUNTIF(Q16:Q79,Q11) -> 0 | S90: =COUNTIF(S16:S79,Q11) -> 0
E92: ADITAMENTO | G92: =SUMIF(I16:I79,E92,G16:G79) -> 0 | K92: SD | M92: RC | O92: AF | Q92: CONTRAPARTIDA | S92: ENTREGA
C94: FINALIZADA | K94: =K89/K86 -> 0 | M94: =M89/M86 -> 0 | O94: =O89/O86 -> 0 | Q94: =Q89/Q86 -> 0 | S94: =S89/S86 -> 0
C96: EM ANDAMENTO | K96: =K88/K86 -> 0 | M96: =M88/M86 -> 0 | O96: =O88/O86 -> 0 | Q96: =Q88/Q86 -> 1 | S96: =S88/S86 -> 1
C98: ATENÇÃO | K98: =K87/K86 -> 0 | M98: =M87/M86 -> 0 | O98: =O87/O86 -> 0 | Q98: =Q87/Q86 -> 0 | S98: =S87/S86 -> 0
G101: =G83+G85 -> 533443.59

Sheet UBS VL INDUSTRIAL
B1: UBS - Unidade Básica de Saúde Vila Industrial
B3: ESTIMATIVA DE ENTREGA: | K3: 46367 | M3: RESTAM : | O3: =K3-TODAY() -> 177 | Q3: DIAS
B5: OBJETIVO
B6: Acompanhar, monitorar e controlar as etapas da execução da obra, bem como a aquisição de equipamentos necessários para seu pleno funcionamento. Problema: Risco de descompasso entre o término das obras e a aquisição de materiais e equipamentos. Solução: Implantar ferramenta única para organizar e acompanhar as aquisições por unidade, conforme o cronograma das obras. Benefício: Garantir início de funcionamento sem atrasos, com melhor planejamento e integração entre as áreas. | Q6: LEGENDA
Q8: 1 | S8: 1. Atenção | U8: Em processo de cotação
Q9: 2 | S9: 2. Em andamento | U9: Em processo de compra
Q10: 3 | S10: 3. Finalizado | U10: Entregue
Q11: 4 | S11: 4. Não Necessita
G12: ******** | I12: representa valor atualizado pelo Mapa de Preço
B16: QTDE | C16: ITENS | E16: Valor Unitário (Estimado) | G16: Valor Total (Estimado) | I16: FONTE DE COMPRA | K16: SD | M16: RC | O16: AF | Q16: CONTRAPARTIDA | S16: ENTREGA | U16: COMPLEMENTO
B18: 2 | C18: APARELHO DE ULTRASSOM / ODONTOLOGICO | E18: 2574.05 | G18: =B18*E18 -> 5148.1 | I18: HUMANITAS | K18: 4 | M18: 4 | O18: 4 | Q18: 2 | S18: 2 | U18: EXPEDIENTE 35449/2026 enviado ao Sr Otavio no dia 18/05/2026. Enviado ao DPSS para cotação no dia 26/02 - alteração necessárias no dia 03/03 - ENCERRADA no dia 04/03 as demais alterações necessárias
B19: 1 | C19: ARQUIVO DE FICHA DE AÇO - 06 GAVETAS (UTILIZADO NA SALA DE VACINA) | E19: 1955.98 | G19: =B19*E19 -> 1955.98 | I19: HUMANITAS | K19: 4 | M19: 4 | O19: 4 | Q19: 2 | S19: 2 | U19: EXPEDIENTE 34459/2026 enviado ao Sr Otavio dia 14/05/2026. Enviado ao DPSS para cotação no dia 26/02 - alteração necessárias no dia 03/03 - ENCERRADA no dia 04/03 as demais alterações necessárias
B20: 1 | C20: ASPIRADOR DE SECREÇÃO PORTATIL C/ RODÍZIO | E20: 3490 | G20: =B20*E20 -> 3490 | I20: HUMANITAS | K20: 4 | M20: 4 | O20: 4 | Q20: 2 | S20: 2 | U20: EXPEDIENTE 39664/2026 enviado ao Sr Otavio dia 01/06/2026. Enviado ao DPSS para cotação no dia 26/02 - alteração necessárias no dia 03/03 - ENCERRADA no dia 04/03 as demais alterações necessárias
B21: 1 | C21: AUTOCLAVE - 54 LITROS | E21: 25263.28 | G21: =B21*E21 -> 25263.28 | I21: HUMANITAS | K21: 4 | M21: 4 | O21: 4 | Q21: 2 | S21: 2 | U21: EXPEDIENTE 35449/2026 enviado ao Sr Otavio no dia 18/05/2026. Enviado ao DPSS para cotação no dia 26/02 - alteração necessárias no dia 03/03 - ENCERRADA no dia 04/03 as demais alterações necessárias
B22: 1 | C22: AVENTAL DE CHUMBO ADULTO - ODONTO | E22: 901.58 | G22: =B22*E22 -> 901.58 | I22: HUMANITAS | K22: 4 | M22: 4 | O22: 4 | Q22: 2 | S22: 2 | U22: EXPEDIENTE 35449/2026 enviado ao Sr Otavio no dia 18/05/2026. Enviado ao DPSS para cotação no dia 26/02 - alteração necessárias no dia 03/03 - ENCERRADA no dia 04/03 as demais alterações necessárias
B23: 1 | C23: AVENTAL DE CHUMBO INFANTIL - PLUBÍFERO / ODONTO | E23: 501.05 | G23: =B23*E23 -> 501.05 | I23: HUMANITAS | K23: 4 | M23: 4 | O23: 4 | Q23: 2 | S23: 2 | U23: EXPEDIENTE 39664/2026 enviado ao Sr Otavio dia 01/06/2026. Enviado ao DPSS para cotação no dia 26/02 - alteração necessárias no dia 03/03 - ENCERRADA no dia 04/03 as demais alterações necessárias
B24: 10 | C24: BALANÇA ADULTO DIGITAL | E24: 1714.65 | G24: =B24*E24 -> 17146.5 | I24: HUMANITAS | K24: 4 | M24: 4 | O24: 4 | Q24: 2 | S24: 2 | U24: EXPEDIENTE 39664/2026 enviado ao Sr Otavio dia 01/06/2026. Enviado ao DPSS para cotação no dia 26/02 - alteração necessárias no dia 03/03 - ENCERRADA no dia 04/03 as demais alterações necessárias
B25: 9 | C25: BALANÇA INFANTIL | E25: 990 | G25: =B25*E25 -> 8910 | I25: HUMANITAS | K25: 4 | M25: 4 | O25: 4 | Q25: 2 | S25: 2 | U25: EXPEDIENTE 35449/2026 enviado ao Sr Otavio no dia 18/05/2026. Enviado ao DPSS para cotação no dia 26/02 - alteração necessárias no dia 03/03 - ENCERRADA no dia 04/03 as demais alterações necessárias
B26: 1 | C26: CADEIRA ALTA / TOTEM | E26: 330 | G26: =B26*E26 -> 330 | I26: HUMANITAS | K26: 4 | M26: 4 | O26: 4 | Q26: 2 | S26: 2 | U26: EXPEDIENTE 34459/2026 enviado ao Sr Otavio dia 14/05/2026. Enviado ao DPSS para cotação no dia 26/02 - alteração necessárias no dia 03/03 - ENCERRADA no dia 04/03 as demais alterações necessárias
B27: 27 | C27: CADEIRA ERGOMÉTRICA PARA FUNCIONÁRIO / COM BRAÇO E RODIZIO | E27: 348 | G27: =B27*E27 -> 9396 | I27: HUMANITAS | K27: 4 | M27: 4 | O27: 4 | Q27: 2 | S27: 2 | U27: EXPEDIENTE 34459/2026 enviado ao Sr Otavio dia 14/05/2026. Enviado ao DPSS para cotação no dia 26/02 - alteração necessárias no dia 03/03 - ENCERRADA no dia 04/03 as demais alterações necessárias
B28: 2 | C28: CADEIRA ODONTOLOGICA COMPLETA | E28: 15090 | G28: =B28*E28 -> 30180 | I28: HUMANITAS | K28: 4 | M28: 4 | O28: 4 | Q28: 2 | S28: 2 | U28: EXPEDIENTE 39664/2026 enviado ao Sr Otavio dia 01/06/2026. Enviado ao DPSS para cotação no dia 26/02 - alteração necessárias no dia 03/03 - ENCERRADA no dia 04/03 as demais alterações necessárias
B29: 38 | C29: CADEIRA PARA PACIENTE / SEM BRAÇO E FIXA | E29: 283 | G29: =B29*E29 -> 10754 | I29: HUMANITAS | K29: 4 | M29: 4 | O29: 4 | Q29: 2 | S29: 2 | U29: EXPEDIENTE 34459/2026 enviado ao Sr Otavio dia 14/05/2026. Enviado ao DPSS para cotação no dia 26/02 - alteração necessárias no dia 03/03 - ENCERRADA no dia 04/03 as demais alterações necessárias
... B44: 9 | C44: MACA COMPLETA - MDF BRANCA MULT COM ARMÁRIO | E44: 2520 | G44: =B44*E44 -> 22680 | I44: HUMANITAS | K44: 4 | M44: 4 | O44: 4 | Q44: 2 | S44: 2 | U44: EXPEDIENTE 39664/2026 enviado ao Sr Otavio dia 01/06/2026. Enviado ao DPSS para cotação no dia 26/02 - alteração necessárias no dia 03/03 - ENCERRADA no dia 04/03 as demais alterações necessárias
B45: 1 | C45: MACA SIMPLES DE RODIZIO | E45: 1366.2 | G45: =B45*E45 -> 1366.2 | I45: HUMANITAS | K45: 4 | M45: 4 | O45: 4 | Q45: 2 | R45: 4 | S45: 2 | U45: EXPEDIENTE 39664/2026 enviado ao Sr Otavio dia 01/06/2026. Enviado ao DPSS para cotação no dia 26/02 - alteração necessárias no dia 03/03 - ENCERRADA no dia 04/03 as demais alterações necessárias
B46: 2 | C46: MESA AUXILIAR INOX - ODONTO | E46: 474.95 | G46: =B46*E46 -> 949.9 | I46: HUMANITAS | K46: 4 | M46: 4 | O46: 4 | Q46: 2 | S46: 2 | U46: EXPEDIENTE 39664/2026 enviado ao Sr Otavio dia 01/06/2026. Enviado ao DPSS para cotação no dia 26/02 - alteração necessárias no dia 03/03 - ENCERRADA no dia 04/03 as demais alterações necessárias
B47: 1 | C47: MICROONDAS - 20 LITROS (CURATIVO) | E47: 649.6 | G47: =B47*E47 -> 649.6 | I47: HUMANITAS | K47: 4 | M47: 4 | O47: 4 | Q47: 2 | S47: 2 | U47: EXPEDIENTE 32629/2026 enviado ao Sr Otavio na data 08/05/2026 - Enviado ao DPSS para cotação no dia 26/02 - alteração necessárias no dia 03/03 - ENCERRADA no dia 04/03 as demais alterações necessárias.
B48: 12 | C48: MOCHO (CONSULTORIOS / ODONTO) | E48: 450 | G48: =B48*E48 -> 5400 | I48: HUMANITAS | K48: 4 | M48: 4 | O48: 4 | Q48: 2 | S48: 2 | U48: EXPEDIENTE 39664/2026 enviado ao Sr Otavio dia 01/06/2026. Enviado ao DPSS para cotação no dia 26/02 - alteração necessárias no dia 03/03 - ENCERRADA no dia 04/03 as demais alterações necessárias
B49: 4 | C49: OTOSCOPIO COMPLETO | E49: 343.5 | G49: =B49*E49 -> 1374 | I49: HUMANITAS | K49: 4 | M49: 4 | O49: 4 | Q49: 2 | S49: 2 | U49: EXPEDIENTE 32629/2026 enviado ao Sr Otavio na data 08/05/2026 - Enviado ao DPSS para cotação no dia 26/02 - alteração necessárias no dia 03/03 - ENCERRADA no dia 04/03 as demais alterações necessárias.
B50: 4 | C50: OXIMENTRO DE PULSO | E50: 84 | G50: =B50*E50 -> 336 | I50: HUMANITAS | K50: 4 | M50: 4 | O50: 4 | Q50: 2 | S50: 2 | U50: EXPEDIENTE 32629/2026 enviado ao Sr Otavio na data 08/05/2026 - Enviado ao DPSS para cotação no dia 26/02 - alteração necessárias no dia 03/03 - ENCERRADA no dia 04/03 as demais alterações necessárias.
B51: 2 | C51: RASPBERRY (TV DA RECEPÇÃO 01) | E51: 2249.9 | G51: =B51*E51 -> 4499.8 | I51: HUMANITAS | K51: 4 | M51: 4 | O51: 4 | Q51: 2 | S51: 2 | U51: EXPEDIENTE 32629/2026 enviado ao Sr Otavio na data 08/05/2026 - Enviado ao DPSS para cotação no dia 26/02 - alteração necessárias no dia 03/03 - ENCERRADA no dia 04/03 as demais alterações necessárias.
B52: 9 | C52: RÉGUA ANTROPOMETRICA - MADEIRA | E52: 88.5 | G52: =B52*E52 -> 796.5 | I52: HUMANITAS | K52: 4 | M52: 4 | O52: 4 | Q52: 2 | S52: 2 | U52: EXPEDIENTE 32629/2026 enviado ao Sr Otavio na data 08/05/2026 - Enviado ao DPSS para cotação no dia 26/02 - alteração necessárias no dia 03/03 - ENCERRADA no dia 04/03 as demais alterações necessárias.
B53: 12 | C53: LONGARINA OTI PE METAL - 02 LUGARES | E53: 2602 | G53: =B53*E53 -> 31224 | I53: HUMANITAS | K53: 4 | M53: 4 | O53: 4 | Q53: 2 | S53: 2 | U53: Está contemplado no EXP. 23951/2026
B54: 16 | C54: LONGARINA OTI PE METAL - 03 LUGARES | E54: 3573 | G54: =B54*E54 -> 57168 | I54: HUMANITAS | K54: 4 | M54: 4 | O54: 4 | Q54: 2 | S54: 2 | U54: Está contemplado no EXP. 23951/2026
B55: 8 | C55: LONGARINA OTI PE METAL - POLATRONA PLUS | E55: 1920 | G55: =B55*E55 -> 15360 | I55: HUMANITAS | K55: 4 | M55: 4 | O55: 4 | Q55: 2 | S55: 2 | U55: Está contemplado no EXP. 23951/2026
B56: 1 | C56: PROJETO MARCENARIA | E56: 218638 | G56: =B56*E56 -> 218638 | I56: HUMANITAS | K56: 4 | M56: 4 | O56: 4 | Q56: 3 | S56: 3 | U56: EXPEDIENTE 15998/2026 enviado ao DGOC em 11/03/2026
B57: 1 | C57: TERMOHEGROMETRO | E57: 98 | G57: =B57*E57 -> 98 | I57: HUMANITAS | K57: 4 | M57: 4 | O57: 4 | Q57: 2 | S57: 2 | U57: EXPEDIENTE 32629/2026 enviado ao Sr Otavio na data 08/05/2026 - Enviado ao DPSS para cotação no dia 26/02 - alteração necessárias no dia 03/03 - ENCERRADA no dia 04/03 as demais alterações necessárias.
B58: 2 | C58: APARELHO DE TV 50" - RECEPÇÃO 01 | E58: 2600 | G58: =B58*E58 -> 5200 | I58: HUMANITAS | K58: 4 | M58: 4 | O58: 4 | Q58: 2 | S58: 2 | U58: EXPEDIENTE 32629/2026 enviado ao Sr Otavio na data 08/05/2026 - Enviado ao DPSS para cotação no dia 26/02 - alteração necessárias no dia 03/03 - ENCERRADA no dia 04/03 as demais alterações necessárias.
C60: TOTAL | G60: =SUM(G18:G58) -> 500370.51
E62: HUMANITAS | G62: =SUMIF(I18:I58,E62,G18:G58) -> 500370.51
E64: PREFEITURA | G64: =SUMIF(I18:I58,E64,G18:G58) -> 0
C65: Total | K65: =SUM(K66:K69) -> 41 | M65: =SUM(M66:M69) -> 41 | O65: =SUM(O66:O69) -> 41 | Q65: =SUM(Q66:Q69) -> 41 | S65: =SUM(S66:S69) -> 41
C66: Atenção | K66: =COUNTIF(K18:K58,Q8) -> 0 | M66: =COUNTIF(M18:M58,Q8) -> 0 | O66: =COUNTIF(O18:O58,Q8) -> 0 | Q66: =COUNTIF(Q18:Q58,Q8) -> 0 | S66: =COUNTIF(S18:S58,Q8) -> 0
C67: Em andamento | K67: =COUNTIF(K18:K58,Q9) -> 0 | M67: =COUNTIF(M18:M58,Q9) -> 0 | O67: =COUNTIF(O18:O58,Q9) -> 0 | Q67: =COUNTIF(Q18:Q58,Q9) -> 40 | S67: =COUNTIF(S18:S58,Q9) -> 40
C68: Finalizado | K68: =COUNTIF(H18:K58,Q10) -> 0 | M68: =COUNTIF(M18:M58,Q10) -> 0 | O68: =COUNTIF(O18:O58,Q10) -> 0 | Q68: =COUNTIF(Q18:Q58,Q10) -> 1 | S68: =COUNTIF(S18:S58,Q10) -> 1
C69: Não Necessita | K69: =COUNTIF(K18:K58,Q11) -> 41 | M69: =COUNTIF(M18:M58,Q11) -> 41 | O69: =COUNTIF(O18:O58,Q11) -> 41 | Q69: =COUNTIF(Q18:Q58,Q11) -> 0 | S69: =COUNTIF(S18:S58,Q11) -> 0
E71: ADITAMENTO | G71: =SUMIF(I18:I58,E71,G18:G58) -> 0 | K71: SD | M71: RC | O71: AF | Q71: CONTRAPARTIDA | S71: ENTREGA
C73: FINALIZADA | K73: =K68/K65 -> 0 | M73: =M68/M65 -> 0 | O73: =O68/O65 -> 0 | Q73: =Q68/Q65 -> 0.024390244 | S73: =S68/S65 -> 0.024390244
C75: EM ANDAMENTO | K75: =K67/K65 -> 0 | M75: =M67/M65 -> 0 | O75: =O67/O65 -> 0 | Q75: =Q67/Q65 -> 0.97560976 | S75: =S67/S65 -> 0.97560976
C77: ATENÇÃO | K77: =K66/K65 -> 0 | M77: =M66/M65 -> 0 | O77: =O66/O65 -> 0 | Q77: =Q66/Q65 -> 0 | S77: =S66/S65 -> 0
G80: =G62+G64 -> 500370.51

Sheet CER III
B1: CER - Centro Especializado em Reabilitação - Tipo III
B3: ESTIMATIVA DE ENTREGA: | K3: 46217 | M3: RESTAM : | O3: =K3-TODAY() -> 27 | Q3: DIAS
B5: OBJETIVO
B6: Acompanhar, monitorar e controlar as etapas da execução da obra, bem como a aquisição de equipamentos necessários para seu pleno funcionamento. Problema: Risco de descompasso entre o término das obras e a aquisição de materiais e equipamentos. Solução: Implantar ferramenta única para organizar e acompanhar as aquisições por unidade, conforme o cronograma das obras. Benefício: Garantir início de funcionamento sem atrasos, com melhor planejamento e integração entre as áreas. | Q6: LEGENDA
Q8: 1 | S8: 1. Atenção
Q9: 2 | S9: 2. Em andamento
Q10: 3 | S10: 3. Finalizado
Q11: 4 | S11: 4. Não Necessita
B14: QTDE | C14: ITENS | E14: Valor Unitário (Estimado) | G14: Valor Total (Estimado) | I14: FONTE DE COMPRA | K14: SD | M14: RC | O14: AF | Q14: CONTRAPARTIDA | S14: ENTREGA | U14: COMPLEMENTO | W14: TIPO DE CONTRATAÇÃO
B16: 18 | C16: Armário para escritório e deposito fisio/ostomia/limpeza | E16: 993 | G16: =PRODUCT(B16,E16) -> 17874 | I16: PREFEITURA | K16: 3 | M16: 3 | O16: 2 | Q16: 4 | S16: 1 | U16: SD 1235 / RC 1918 ENCAMINHADO AO COMPRAS EM 12/03 - PE 88/2026 - AB 22/06 | W16: LICITAÇÃO
B17: 28 | C17: Armário para consultórios | E17: 635 | G17: =PRODUCT(B17,E17) -> 17780 | I17: PREFEITURA | K17: 3 | M17: 3 | O17: 2 | Q17: 4 | S17: 1 | U17: SD 1235 / RC 1918 ENCAMINHADO AO COMPRAS EM 12/03 - PE 88/2026 - AB 22/06 | W17: LICITAÇÃO
B18: 6 | C18: Suporte para microondas | E18: 87 | G18: =PRODUCT(B18,E18) -> 522 | I18: PREFEITURA | K18: 3 | M18: 3 | O18: 2 | Q18: 4 | S18: 1 | U18: SD 1236 / RC 1914 ENCAMINHADO AO COMPRAS EM 12/03 - PE 88/2026 - AB 22/06 | W18: LICITAÇÃO
B19: 7 | C19: Arquivo de aço | E19: 1460 | G19: =PRODUCT(B19,E19) -> 10220 | I19: PREFEITURA | K19: 3 | M19: 3 | O19: 2 | Q19: 4 | S19: 1 | U19: SD 1236 / RC 1914 ENCAMINHADO AO COMPRAS EM 12/03 - PE 88/2026 - AB 22/06 | W19: LICITAÇÃO
B20: 11 | C20: Gaveteiro volante para impressora | E20: 363 | G20: =PRODUCT(B20,E20) -> 3993 | I20: PREFEITURA | K20: 3 | M20: 3 | O20: 2 | Q20: 4 | S20: 1 | U20: SD 1236 / RC 1914 ENCAMINHADO AO COMPRAS EM 12/03 - PE 88/2026 - AB 22/06 | W20: LICITAÇÃO
B21: 35 | C21: suporte para CPU | E21: 209.9 | G21: =PRODUCT(B21,E21) -> 7346.5 | I21: PREFEITURA | K21: 3 | M21: 2 | O21: 1 | Q21: 4 | S21: 1 | U21: SD 2631
B22: 3 | C22: Biombo | E22: 677.5 | G22: =PRODUCT(B22,E22) -> 2032.5 | I22: PREFEITURA | K22: 3 | M22: 3 | O22: 3 | Q22: 4 | S22: 3 | U22: SD 872 - RC 1748 - ENCAMINHADO AO COMPRAS EM 06/03 - VISTORIADO EM 12/06 | W22: COMPRA DIRETA
B23: 4 | C23: Cadeiras infantis da área de convenincia | E23: 170 | G23: =PRODUCT(B23,E23) -> 680 | I23: PREFEITURA | K23: 3 | M23: 3 | O23: 3 | Q23: 4 | S23: 3 | U23: SD 1233 / RC 1909 ENCAMINHADO AO COMPRAS EM 12/03 - ITEM CANCELADO | W23: LICITAÇÃO
B24: 2 | C24: Cadeira de rodas obeso | E24: 2890 | G24: =PRODUCT(B24,E24) -> 5780 | I24: PREFEITURA | K24: 3 | M24: 3 | O24: 3 | Q24: 4 | S24: 2 | U24: SD 926 - RC 1792 - ENCAMINHADO AO COMPRAS EM 06/03 | W24: COMPRA DIRETA
B25: 6 | C25: Poltrona para Administração/coordenação | E25: 479 | G25: =PRODUCT(B25,E25) -> 2874 | I25: PREFEITURA | K25: 3 | M25: 3 | O25: 2 | Q25: 4 | S25: 1 | U25: SD 1236 / RC 1914 ENCAMINHADO AO COMPRAS EM 12/03 - PE 88/2026 - AB 22/06 | W25: LICITAÇÃO
B26: 67 | C26: Cadeira Fixa | E26: 86.4 | G26: =PRODUCT(B26,E26) -> 5788.8 | I26: PREFEITURA | K26: 3 | M26: 3 | O26: 3 | Q26: 4 | S26: 2 | U26: SD 1233 / RC 1909 ENCAMINHADO AO COMPRAS EM 12/03 - AF 3525 | W26: COMPRA DIRETA
B27: 28 | C27: Cadeira giratória (45 funcionários) | E27: 493 | G27: =PRODUCT(B27,E27) -> 13804 | I27: PREFEITURA | K27: 3 | M27: 3 | O27: 3 | Q27: 4 | S27: 3 | U27: SD 1233 / RC 1909 ENCAMINHADO AO COMPRAS EM 12/03 - AF 3538 - VISTORIA 12/06 | W27: COMPRA DIRETA
B28: 4 | C28: Televisor de 50 plegadas | E28: 2250 | G28: =PRODUCT(B28,E28) -> 9000 | I28: PREFEITURA | K28: 3 | M28: 3 | O28: 3 | Q28: 4 | S28: 3 | U28: SD - 874 / RC 1907 ENCAMINHADO AO COMPRAS EM 12/03 - vistoria 29/05 | W28: COMPRA DIRETA
B29: 1 | C29: Televisor de 75 polegadas | E29: 3700 | G29: =PRODUCT(B29,E29) -> 3700 | I29: PREFEITURA | K29: 3 | M29: 3 | O29: 3 | Q29: 4 | S29: 3 | U29: SD - 874 / RC 1907 ENCAMINHADO AO COMPRAS EM 12/03 - VISTORIA 12/06 | W29: COMPRA DIRETA
B30: 3 | C30: Mesa para cozinha de 6 lugares | E30: 1180 | G30: =PRODUCT(B30,E30) -> 3540 | I30: PREFEITURA | K30: 3 | M30: 3 | O30: 2 | Q30: 4 | S30: 1 | U30: SD 1234 / RC 1917 ENCAMINHADO AO COMPRAS EM 12/03 - PE 88/2026 AB 22/06 | W30: LICITAÇÃO
B31: 5 | C31: Mesa Administrativa | E31: 1339.5 | G31: =PRODUCT(B31,E31) -> 6697.5 | I31: PREFEITURA | K31: 3 | M31: 3 | O31: 2 | Q31: 4 | S31: 1 | U31: SD 1234 / RC 1917 ENCAMINHADO AO COMPRAS EM 12/03 - PE 88/2026 AB 22/06 | W31: LICITAÇÃO
B32: 1 | C32: Mesa Coordenação | E32: 1849 | G32: =PRODUCT(B32,E32) -> 1849 | I32: PREFEITURA | K32: 3 | M32: 3 | O32: 2 | Q32: 4 | S32: 1 | U32: SD 1234 / RC 1917 ENCAMINHADO AO COMPRAS EM 12/03 - PE 88/2026 AB 22/06 | W32: LICITAÇÃO
B33: 29 | C33: Mesa recepção/consultório | E33: 1079 | G33: =PRODUCT(B33,E33) -> 31291 | I33: PREFEITURA | K33: 3 | M33: 3 | O33: 2 | Q33: 4 | S33: 1 | U33: SD 1234 / RC 1917 ENCAMINHADO AO COMPRAS EM 12/03 - PE 88/2026 AB 22/06 | W33: LICITAÇÃO
... B38: 12 | C38: Escada 2 degraus | E38: 260.5 | G38: =PRODUCT(B38,E38) -> 3126 | I38: PREFEITURA | K38: 3 | M38: 3 | O38: 2 | Q38: 4 | S38: 1 | U38: SD 1236 / RC 1914 ENCAMINHADO AO COMPRAS EM 12/03 - PE 88/2026 - AB 22/06 | W38: LICITAÇÃO
B39: 9 | C39: Conjunto mesa c/4 cadeiras infantil para salas de terapia | E39: 931 | G39: =PRODUCT(B39,E39) -> 8379 | I39: PREFEITURA | K39: 3 | M39: 3 | O39: 2 | Q39: 4 | S39: 1 | U39: SD 2120 - RC 3783
B40: 1 | C40: Lanterna Clínica | E40: 53.46 | G40: =PRODUCT(B40,E40) -> 53.46 | I40: PREFEITURA | K40: 3 | M40: 3 | O40: 3 | Q40: 4 | S40: 3 | U40: SD 881 / RC 1900 ENCAMINHADO AO COMPRAS EM 12/03 VISTORIADO EM 30/04 | W40: COMPRA DIRETA
B41: 1 | C41: Nebulizador Portátil | E41: 205 | G41: =PRODUCT(B41,E41) -> 205 | I41: PREFEITURA | K41: 3 | M41: 3 | O41: 3 | Q41: 4 | S41: 3 | U41: SD 881 / RC 1900 ENCAMINHADO AO COMPRAS EM 12/03 VISTORIADO EM 08/05 | W41: COMPRA DIRETA
B42: 4 | C42: Cronômetro | E42: 22.5 | G42: =PRODUCT(B42,E42) -> 90 | I42: PREFEITURA | K42: 3 | M42: 3 | O42: 3 | Q42: 4 | S42: 3 | U42: SD 877 - RC 1795 - AF 2388 E 2390 VISTORIADO EM 30/04 | W42: COMPRA DIRETA
B43: 1 | C43: Aspirador de secreções | E43: 2619.6 | G43: =PRODUCT(B43,E43) -> 2619.6 | I43: PREFEITURA | K43: 3 | M43: 3 | O43: 3 | Q43: 4 | S43: 3 | U43: SD 881 / RC 1900 ENCAMINHADO AO COMPRAS EM 12/03 - VISTORIA EM 29/05 | W43: COMPRA DIRETA
B44: 2 | C44: Fotóforo | E44: 2850 | G44: =PRODUCT(B44,E44) -> 5700 | I44: PREFEITURA | K44: 3 | M44: 3 | O44: 3 | Q44: 4 | S44: 3 | U44: SD 881 / RC 1900 ENCAMINHADO AO COMPRAS EM 12/03 - entregue 01 em 08/05 | W44: COMPRA DIRETA
B45: 1 | C45: Glicosímetro | E45: 123 | G45: =PRODUCT(B45,E45) -> 123 | I45: PREFEITURA | K45: 3 | M45: 3 | O45: 3 | Q45: 4 | S45: 3 | U45: SD 881 / RC 1900 ENCAMINHADO AO COMPRAS EM 12/03 VISTORIADO EM 08/05 | W45: COMPRA DIRETA
B46: 10 | C46: Mocho | E46: 910 | G46: =PRODUCT(B46,E46) -> 9100 | I46: PREFEITURA | K46: 3 | M46: 3 | O46: 3 | Q46: 4 | S46: 3 | U46: SD 881 / RC 1900 ENCAMINHADO AO COMPRAS EM 12/03 VISTORIADO EM 08/05 | W46: COMPRA DIRETA
B47: 1 | C47: Reanimador Pulmonar Manual Adulto (Ambu) | E47: 149.49 | G47: =PRODUCT(B47,E47) -> 149.49 | I47: PREFEITURA | K47: 3 | M47: 3 | O47: 3 | Q47: 4 | S47: 3 | U47: SD 880 / RC -1742 / AF 2241 VISTORIADO EM 30/04 | W47: COMPRA DIRETA
B48: 1 | C48: Balança Antropométrica Infantil | E48: 850 | G48: =PRODUCT(B48,E48) -> 850 | I48: PREFEITURA | K48: 3 | M48: 3 | O48: 3 | Q48: 4 | S48: 3 | U48: SD 877 - RC 1795 - AF 2388 E 2390 - VISTORIADO EM 19/05 | W48: COMPRA DIRETA
B49: 1 | C49: Balança Antropométrica Adulto | E49: 960 | G49: =PRODUCT(B49,E49) -> 960 | I49: PREFEITURA | K49: 3 | M49: 3 | O49: 3 | Q49: 4 | S49: 3 | U49: SD 877 - RC 1795 - AF 2388 E 2390 - VISTORIADO EM 19/05 | W49: COMPRA DIRETA
B50: 2 | C50: DEA – Desfibrilador Externo Automático | E50: 7936 | G50: =PRODUCT(B50,E50) -> 15872 | I50: PREFEITURA | K50: 3 | M50: 3 | O50: 3 | Q50: 4 | S50: 3 | U50: SD 880 / RC -1742 / AF 2241 VISTORIADO EM 30/04 | W50: COMPRA DIRETA
B51: 1 | C51: Trocador de Fraldas de Parede Infantil | E51: 790 | G51: =PRODUCT(B51,E51) -> 790 | I51: PREFEITURA | K51: 3 | M51: 3 | O51: 2 | Q51: 4 | S51: 1 | U51: SD 1236 / RC 1914 ENCAMINHADO AO COMPRAS EM 12/03 - PE 88/2026 - AB 22/06 | W51: LICITAÇÃO
... B58: 1 | C58: Ganho de Inserção - Aparelho audiológico | E58: 41300 | G58: =PRODUCT(B58,E58) -> 41300 | I58: PREFEITURA | K58: 3 | M58: 3 | O58: 2 | Q58: 4 | S58: 1 | U58: SD 922 - RC 2382 - ENCAMINHADO AO COMPRAS EM 26/03 | W58: COMPRA DIRETA
B59: 1 | C59: Sistema de Campo Livre* | E59: 3180 | G59: =PRODUCT(B59,E59) -> 3180 | H59: =PRODUCT(C59,F59) -> 0 | I59: PREFEITURA | K59: 3 | M59: 3 | O59: 2 | Q59: 4 | S59: 1 | U59: SD 922 - RC 2382 - ENCAMINHADO AO COMPRAS EM 26/03 | W59: COMPRA DIRETA
B60: 1 | C60: Videolaringoscópio | E60: 14980 | G60: =PRODUCT(B60,E60) -> 14980 | I60: PREFEITURA | K60: 3 | M60: 3 | O60: 2 | S60: 1 | U60: SD 922 - RC 2382 - ENCAMINHADO AO COMPRAS EM 26/03 | W60: COMPRA DIRETA
B61: 2 | C61: Otoscópio | E61: 370 | G61: =PRODUCT(B61,E61) -> 740 | I61: PREFEITURA | K61: 3 | M61: 3 | O61: 3 | Q61: 4 | S61: 2 | U61: SD 881 / RC 1900 ENCAMINHADO AO COMPRAS EM 12/03 | W61: COMPRA DIRETA
B62: 1 | C62: Autoclave | E62: 5133 | G62: =PRODUCT(B62,E62) -> 5133 | I62: PREFEITURA | K62: 3 | M62: 3 | O62: 3 | Q62: 4 | S62: 3 | U62: SD 881 / RC 1900 ENCAMINHADO AO COMPRAS EM 12/03 VISTORIADO EM 08/05 | W62: COMPRA DIRETA
B63: 5 | C63: Espéculo Nasal adulto | E63: 39.6 | G63: =PRODUCT(B63,E63) -> 198 | I63: PREFEITURA | K63: 3 | M63: 3 | O63: 3 | Q63: 4 | S63: 3 | U63: SD 921 - RC 1752 - ENCAMINHADO AO COMPRAS EM 06/03 - VISTORIA 12/06 | W63: COMPRA DIRETA
B64: 5 | C64: Espéculo Nasal infantil | E64: 39.6 | G64: =PRODUCT(B64,E64) -> 198 | I64: PREFEITURA | K64: 3 | M64: 3 | O64: 3 | Q64: 4 | S64: 3 | U64: SD 921 - RC 1752 - ENCAMINHADO AO COMPRAS EM 06/03 - VISTORIA 12/06 | W64: COMPRA DIRETA
B65: 15 | C65: Espéculo Auricular | E65: 14.4 | G65: =PRODUCT(B65,E65) -> 216 | I65: PREFEITURA | K65: 3 | M65: 3 | O65: 3 | Q65: 4 | S65: 3 | U65: SD 921 - RC 1752 - ENCAMINHADO AO COMPRAS EM 06/03 VISTORIADO EM 08/05 | W65: COMPRA DIRETA
B66: 2 | C66: Pinças em baioneta com dente 21 | E66: 49 | G66: =PRODUCT(B66,E66) -> 98 | I66: PREFEITURA | K66: 3 | M66: 3 | O66: 3 | Q66: 4 | S66: 3 | U66: SD 881 / RC 1900 ENCAMINHADO AO COMPRAS EM 12/03 VISTORIADO EM 08/05 | W66: COMPRA DIRETA
B67: 2 | C67: Pinças em baioneta com dente 17 | E67: 36 | G67: =PRODUCT(B67,E67) -> 72 | I67: PREFEITURA | K67: 3 | M67: 3 | O67: 3 | Q67: 4 | S67: 3 | U67: SD 881 / RC 1900 ENCAMINHADO AO COMPRAS EM 12/03 VISTORIADO EM 08/05 | W67: COMPRA DIRETA
B68: 2 | C68: Pinças em baioneta sem dente 21 | E68: 49 | G68: =PRODUCT(B68,E68) -> 98 | I68: PREFEITURA | K68: 3 | M68: 3 | O68: 3 | Q68: 4 | S68: 2 | U68: SD 881 / RC 1900 ENCAMINHADO AO COMPRAS EM 12/03 | W68: COMPRA DIRETA
B69: 2 | C69: Pinças em baioneta sem dente 17 | E69: 32 | G69: =PRODUCT(B69,E69) -> 64 | I69: PREFEITURA | K69: 3 | M69: 3 | O69: 3 | Q69: 4 | S69: 2 | U69: SD 881 / RC 1900 ENCAMINHADO AO COMPRAS EM 12/03 | W69: COMPRA DIRETA
B70: 2 | C70: Pinças em baioneta 16 | E70: 24.6 | G70: =PRODUCT(B70,E70) -> 49.2 | I70: PREFEITURA | K70: 3 | M70: 3 | O70: 3 | Q70: 4 | S70: 3 | U70: SD 921 - RC 1752 - ENCAMINHADO AO COMPRAS EM 06/03 - VISTORIA 12/06 | W70: COMPRA DIRETA
B71: 2 | C71: Pinças em baioneta 14 | E71: 12 | G71: =PRODUCT(B71,E71) -> 24 | I71: PREFEITURA | K71: 3 | M71: 3 | O71: 3 | Q71: 4 | S71: 3 | U71: SD 921 - RC 1752 - ENCAMINHADO AO COMPRAS EM 06/03 - VISTORIA 12/06 | W71: COMPRA DIRETA
B72: 2 | C72: Pinça sem dente 20cm | E72: 7.3 | G72: =PRODUCT(B72,E72) -> 14.6 | I72: PREFEITURA | K72: 3 | M72: 3 | O72: 3 | Q72: 4 | S72: 3 | U72: SD 881 / RC 1900 ENCAMINHADO AO COMPRAS EM 12/03 VISTORIADO EM 08/05 | W72: COMPRA DIRETA
... B85: 2 | C85: Bicicleta Horizontal | E85: 5890 | G85: =PRODUCT(B85,E85) -> 11780 | I85: PREFEITURA | K85: 3 | M85: 3 | O85: 2 | Q85: 4 | S85: 1 | U85: SD 2111 - RC 4012 | W85: COMPRA DIRETA
B86: 1 | C86: Painel sensorial | E86: 2750 | G86: =PRODUCT(B86,E86) -> 2750 | I86: PREFEITURA | K86: 3 | M86: 3 | O86: 2 | S86: 1 | U86: SD 2403 - RC 4583
B87: 2 | C87: Balancim Proprioceptivo | E87: 316.8 | G87: =PRODUCT(B87,E87) -> 633.6 | I87: PREFEITURA | K87: 3 | M87: 3 | O87: 3 | Q87: 4 | S87: 3 | U87: SD 925 - RC 1749 - ENCAMINHADO AO COMPRAS EM 06/03 AF 3676 - VISTORIA 12/06 | W87: COMPRA DIRETA
B88: 2 | C88: Jogo de halteres | E88: 2155 | G88: =PRODUCT(B88,E88) -> 4310 | I88: PREFEITURA | K88: 3 | M88: 3 | O88: 3 | Q88: 4 | S88: 2 | U88: SD 925 - RC 1749 - ENCAMINHADO AO COMPRAS EM 06/03 AF 3676 | W88: COMPRA DIRETA
B89: 4 | C89: Cama Elástica Proprioceptiva | E89: 211.9 | G89: =PRODUCT(B89,E89) -> 847.6 | I89: PREFEITURA | K89: 3 | M89: 3 | O89: 3 | Q89: 4 | S89: 3 | U89: SD 925 - RC 1749 - ENCAMINHADO AO COMPRAS EM 06/03 VISTORIADO EM 08/05 | W89: COMPRA DIRETA
B90: 2 | C90: Cicloergômetro Mini bike | E90: 1100 | G90: =PRODUCT(B90,E90) -> 2200 | I90: PREFEITURA | K90: 3 | M90: 3 | O90: 3 | Q90: 4 | S90: 3 | U90: SD 925 - RC 1749 - ENCAMINHADO AO COMPRAS EM 06/03 VISTORIADO EM 30/04 | W90: COMPRA DIRETA
B91: 1 | C91: Esteira Ergométrica | E91: 12639 | G91: =PRODUCT(B91,E91) -> 12639 | I91: PREFEITURA | K91: 3 | M91: 3 | O91: 2 | Q91: 4 | S91: 1 | U91: SD 2164 - ETP 395 | W91: COMPRA DIRETA
B92: 6 | C92: Monofilamentos | E92: 390 | G92: =PRODUCT(B92,E92) -> 2340 | I92: PREFEITURA | K92: 3 | M92: 3 | O92: 3 | Q92: 4 | S92: 3 | U92: SD 927 - RC 1754 - AF 2421 | W92: COMPRA DIRETA
B93: 8 | C93: Bola suíça tamanho 45 | E93: 63 | G93: =PRODUCT(B93,E93) -> 504 | I93: PREFEITURA | K93: 3 | M93: 3 | O93: 3 | Q93: 4 | S93: 3 | U93: SD 924 - RC 1793 - ENCAMINHADO AO COMPRAS EM 06/03 - VISTORIADO EM 19/05 | W93: COMPRA DIRETA
B94: 6 | C94: Bola suíça tamanho 65 | E94: 46.33 | G94: =PRODUCT(B94,E94) -> 277.98 | I94: PREFEITURA | K94: 3 | M94: 3 | O94: 3 | Q94: 4 | S94: 3 | U94: SD 924 - RC 1793 - ENCAMINHADO AO COMPRAS EM 06/03 | W94: COMPRA DIRETA
B95: 4 | C95: Bola suíça tamanho 85 | E95: 132 | G95: =PRODUCT(B95,E95) -> 528 | I95: PREFEITURA | K95: 3 | M95: 3 | O95: 3 | Q95: 4 | S95: 3 | U95: SD 924 - RC 1793 - ENCAMINHADO AO COMPRAS EM 06/03 - VISTORIADO EM 19/05 | W95: COMPRA DIRETA
B96: 5 | C96: Caneleira 1,0kg | E96: 21.56 | G96: =PRODUCT(B96,E96) -> 107.8 | I96: PREFEITURA | K96: 3 | M96: 3 | O96: 3 | Q96: 4 | S96: 3 | U96: SD 924 - RC 1793 - ENCAMINHADO AO COMPRAS EM 06/03- VISTORIADO EM 29/05 | W96: COMPRA DIRETA
B97: 5 | C97: Caneleira 2,0kg | E97: 25.2 | G97: =PRODUCT(B97,E97) -> 126 | I97: PREFEITURA | K97: 3 | M97: 3 | O97: 3 | Q97: 4 | S97: 3 | U97: SD 924 - RC 1793 - ENCAMINHADO AO COMPRAS EM 06/03 - VISTORIADO EM 29/05 | W97: COMPRA DIRETA
B98: 5 | C98: Caneleira 3,0 kg | E98: 40 | G98: =PRODUCT(B98,E98) -> 200 | I98: PREFEITURA | K98: 3 | M98: 3 | O98: 3 | Q98: 4 | S98: 3 | U98: SD 924 - RC 1793 - ENCAMINHADO AO COMPRAS EM 06/03 - VISTORIADO EM 29/05 | W98: COMPRA DIRETA
... B115: 7 | C115: Espaldar em Madeira (Barra/Escada de Ling) | E115: 400 | G115: =PRODUCT(B115,E115) -> 2800 | I115: PREFEITURA | K115: 3 | M115: 3 | O115: 3 | Q115: 4 | S115: 3 | U115: SD 924 - RC 1793 - ENCAMINHADO AO COMPRAS EM 06/03 VISTORIADO EM 08/05 | W115: COMPRA DIRETA
B116: 24 | C116: Camisa Polo Administrativo | E116: 74.9 | G116: 1797.6 | I116: PREFEITURA | K116: 3 | M116: 3 | O116: 2 | Q116: 4 | S116: 1 | U116: SD 2205 - RC 4013 | W116: COMPRA DIRETA
B117: 12 | C117: Blusa de frio Administrativo | E117: 129.9 | G117: 1558.8 | I117: PREFEITURA | K117: 3 | M117: 3 | O117: 2 | Q117: 4 | S117: 1 | U117: SD 2205 - RC 4013 | W117: COMPRA DIRETA
B118: 100 | C118: Pijama/jaleco | E118: 150 | G118: =PRODUCT(B118,E118) -> 15000 | I118: PREFEITURA | K118: 3 | M118: 3 | O118: 2 | Q118: 4 | S118: 1 | U118: SD 1984 - RC 3799 - ENCAMINHADO AO COMPRAS EM 14/05 | W118: COMPRA DIRETA
B119: 2 | C119: massa terapeutica de silicone | E119: 690 | G119: =PRODUCT(B119,E119) -> 1380 | I119: PREFEITURA | K119: 3 | M119: 3 | O119: 3 | Q119: 4 | S119: 3 | U119: SD 927 - RC 1754 - AF 2421 VISTORIADO EM 30/04 | W119: COMPRA DIRETA
B120: 2 | C120: Circuito espumado | E120: 1500 | G120: =PRODUCT(B120,E120) -> 3000 | I120: PREFEITURA | K120: 3 | M120: 3 | O120: 3 | Q120: 4 | S120: 3 | U120: SD 882 - RC 1740 - AF 3774 ENCAMINHADO AO COMPRAS EM 06/03 - VISTORIA 12/06 | W120: COMPRA DIRETA
B121: 2 | C121: Bosu | E121: 500 | G121: =PRODUCT(B121,E121) -> 1000 | I121: PREFEITURA | K121: 3 | M121: 3 | O121: 3 | Q121: 4 | S121: 2 | U121: SD 926 - RC 1792 - ENCAMINHADO AO COMPRAS EM 06/03 | W121: COMPRA DIRETA
B122: 2 | C122: Digiflex jogo | E122: 23.32 | G122: =PRODUCT(B122,E122) -> 46.64 | I122: PREFEITURA | K122: 3 | M122: 3 | O122: 3 | Q122: 4 | S122: 3 | U122: SD 925 - RC 1749 - ENCAMINHADO AO COMPRAS EM 06/03 VISTORIADO EM 30/04 | W122: COMPRA DIRETA
B123: 1 | C123: Bambolê kit | E123: 53 | G123: =PRODUCT(B123,E123) -> 53 | I123: PREFEITURA | K123: 3 | M123: 3 | O123: 3 | Q123: 4 | S123: 3 | U123: SD 882 - RC 1740 - AF 3774 - ENCAMINHADO AO COMPRAS EM 06/03 - VISTORIA 12/06 | W123: COMPRA DIRETA
B124: 2 | C124: Kit Alinhavo | E124: 77.46 | G124: =PRODUCT(B124,E124) -> 154.92 | I124: PREFEITURA | K124: 3 | M124: 3 | O124: 3 | Q124: 4 | S124: 3 | U124: SD 924 - RC 1793 - ENCAMINHADO AO COMPRAS EM 06/03 VISTORIADO EM 08/05 | W124: COMPRA DIRETA
B125: 4 | C125: Arco tonificador | E125: 63 | G125: =PRODUCT(B125,E125) -> 252 | I125: PREFEITURA | K125: 3 | M125: 3 | O125: 3 | Q125: 4 | S125: 3 | U125: SD 924 - RC 1793 - ENCAMINHADO AO COMPRAS EM 06/03 - VISTORIADO EM 19/05 | W125: COMPRA DIRETA
B126: 2 | C126: Prancha de comunicação alternativa | E126: 127.3 | G126: =PRODUCT(B126,E126) -> 254.6 | I126: PREFEITURA | K126: 3 | M126: 3 | O126: 3 | Q126: 4 | S126: 3 | U126: SD 924 - RC 1793 - ENCAMINHADO AO COMPRAS EM 06/03 - VISTORIADO EM 19/05 | W126: COMPRA DIRETA
B127: 2 | C127: Tesoura para canhoto | E127: 8 | G127: =PRODUCT(B127,E127) -> 16 | I127: PREFEITURA | K127: 3 | M127: 3 | O127: 3 | Q127: 4 | S127: 3 | U127: SD 882 - RC 1740 - ENCAMINHADO AO COMPRAS EM 06/03 AF 3726 - VISTORIA 12/06 | W127: COMPRA DIRETA
B128: 5 | C128: Quadro Branco | E128: 245 | G128: =PRODUCT(B128,E128) -> 1225 | I128: PREFEITURA | K128: 3 | M128: 3 | O128: 3 | Q128: 4 | S128: 3 | U128: SD 1151 RC 1757 - AF 2362 VISTORIADO EM 30/04 | W128: COMPRA DIRETA
B129: 6 | C129: Balde a Pedal médio 30L | E129: 252.38 | G129: =PRODUCT(B129,E129) -> 1514.28 | I129: PREFEITURA | K129: 3 | M129: 3 | O129: 2 | Q129: 4 | S129: 1 | U129: SD - 1181 / RC 1812 e SD 2040 - ENCAMINHADO AO COMPRAS EM 06/03 | W129: COMPRA DIRETA
... B165: 1 | C165: Projetor Multimídia (Datashow) | E165: 5780 | G165: =PRODUCT(B165,E165) -> 5780 | I165: PREFEITURA | K165: 3 | M165: 3 | O165: 3 | Q165: 4 | S165: 3 | U165: SD 1427 - RC 2264- ENCAMINHADO AO COMPRAS EM 26/03 - VISTORIADO EM 19/05 | W165: COMPRA DIRETA
B166: 25 | C166: Telefone (Expediente) | E166: 0 | G166: =PRODUCT(B166,E166) -> 0 | K166: 3 | M166: 3 | O166: 3 | Q166: 4 | S166: 3 | U166: Demanda enviada à telefonia
B167: 60 | C167: Borrifador de alcool | E167: 10 | G167: =PRODUCT(B167,E167) -> 600 | I167: PREFEITURA | K167: 3 | M167: 3 | O167: 2 | Q167: 4 | S167: 1 | U167: SD 2158 RC 3889 - tramitado pra Talita DASS em 14/05 | W167: COMPRA DIRETA
B168: 1 | C168: Sala Multisensorial | E168: 340000 | G168: =PRODUCT(B168,E168) -> 340000 | I168: PREFEITURA | K168: 3 | M168: 3 | O168: 2 | Q168: 4 | S168: 1 | U168: SD 2186 - ETP 407 - NÃO TEM RC
B169: 1 | C169: Balança para cadeirante | E169: 6098 | G169: =PRODUCT(B169,E169) -> 6098 | I169: PREFEITURA | K169: 3 | M169: 3 | O169: 3 | Q169: 4 | S169: 3 | U169: SD 877 - RC 1795 - AF 2388 E 2390 - VISTORIADO EM 19/05 | W169: COMPRA DIRETA
B170: 10 | C170: Bastão para fisioterapia | E170: 20 | G170: =PRODUCT(B170,E170) -> 200 | I170: PREFEITURA | K170: 3 | M170: 3 | O170: 3 | Q170: 4 | S170: 3 | U170: SD 924 - RC 1793 - ENCAMINHADO AO COMPRAS EM 06/03 - VISTORIADO EM 19/05 | W170: COMPRA DIRETA
B171: 1 | C171: Equipamento completo de integração sensorial | E171: 4990 | G171: =PRODUCT(B171,E171) -> 4990 | I171: PREFEITURA | K171: 3 | M171: 3 | O171: 2 | Q171: 4 | S171: 1 | U171: SD 1463 - RC 2386 - ENCAMINHADO AO COMPRAS EM 26/03 | W171: COMPRA DIRETA
B172: 4 | C172: Hand-helper | E172: 70 | G172: =PRODUCT(B172,E172) -> 280 | I172: PREFEITURA | K172: 3 | M172: 3 | O172: 3 | Q172: 4 | S172: 2 | U172: SD 926 - RC 1792 - ENCAMINHADO AO COMPRAS EM 06/03 | W172: COMPRA DIRETA
B173: 1 | C173: Boneco de ostomia | E173: 8600 | G173: =PRODUCT(B173,E173) -> 8600 | I173: PREFEITURA | K173: 3 | M173: 3 | O173: 2 | Q173: 4 | S173: 1 | U173: SD 921 - RC 1752 - ENCAMINHADO AO COMPRAS EM 06/03 | W173: COMPRA DIRETA
B174: 1 | C174: Simulador de cateterização feminino e masculino p/ Ostomia | E174: 4368 | G174: =PRODUCT(B174,E174) -> 4368 | I174: PREFEITURA | K174: 3 | M174: 2 | O174: 1 | Q174: 4 | S174: 1 | U174: SD 2458 - NÃO TEM RC
B175: 5 | C175: Banco bolachão com rodinhas | E175: 249.2 | G175: =PRODUCT(B175,E175) -> 1246 | I175: PREFEITURA | K175: 3 | M175: 3 | O175: 3 | Q175: 4 | S175: 3 | U175: SD 882 - RC 1740 - ENCAMINHADO AO COMPRAS EM 06/03 AF 3729 - VISTORIA 12/06 | W175: COMPRA DIRETA
B176: 1 | C176: Coleção livro das emoções | E176: 375 | G176: =PRODUCT(B176,E176) -> 375 | I176: PREFEITURA | K176: 3 | M176: 3 | O176: 3 | Q176: 4 | S176: 3 | U176: SD 924 - RC 1793 - ENCAMINHADO AO COMPRAS EM 06/03 - VISTORIADO EM 19/05 | W176: COMPRA DIRETA
B177: 34 lugares | C177: Longarina | G177: =PRODUCT(B177,E177) -> 0 | I177: HUMANITAS | K177: 3 | M177: 3 | O177: 3 | Q177: 4 | S177: 2 | U177: CONFORME INFORMAÇÕES REPASSADAS PELA ELAINE, COMPRA SERÁ EM CONJUNTO COM O DAPRIS E DGHE (VIA HUMANITAS)
B178: 1 | C178: Maca obeso | E178: 2849 | G178: =PRODUCT(B178,E178) -> 2849 | I178: PREFEITURA | K178: 3 | M178: 3 | O178: 3 | Q178: 4 | S178: 2 | U178: SD - 928 / RC - 1756 / AF 2924 E 2430 | W178: COMPRA DIRETA
B179: 8 | C179: Poltrona | E179: 455.95 | G179: =PRODUCT(B179,E179) -> 3647.6 | I179: PREFEITURA | K179: 3 | M179: 3 | O179: 3 | Q179: 4 | S179: 2 | U179: SD 872 - RC 1748 - ENCAMINHADO AO COMPRAS EM 06/03 | W179: COMPRA DIRETA
...

Sheet HOSPITAL DE RETAGUARDA
B1: Hospital de Retaguarda
B3: ESTIMATIVA DE ENTREGA: | K3: 46220 | M3: RESTAM : | O3: =K3-TODAY() -> 30 | Q3: DIAS
B5: OBJETIVO | K5: HR será objeto de TA no Contrato de Gestão 501/2022 (Microrregião Leste)
B6: Acompanhar, monitorar e controlar as etapas da execução da obra, bem como a aquisição de equipamentos necessários para seu pleno funcionamento. Problema: Risco de descompasso entre o término das obras e a aquisição de materiais e equipamentos. Solução: Implantar ferramenta única para organizar e acompanhar as aquisições por unidade, conforme o cronograma das obras. Benefício: Garantir início de funcionamento sem atrasos, com melhor planejamento e integração entre as áreas. | Q6: LEGENDA
Q8: 1 | S8: 1. Atenção | U8: Em processo de cotação
Q9: 2 | S9: 2. Em andamento | U9: Em processo de compra
Q10: 3 | S10: 3. Finalizado | U10: Entregue
Q11: 4 | S11: 4. Não Necessita
B14: QTDE | C14: ITENS | E14: Valor Unitário (Estimado) | G14: Valor Total (Estimado) | I14: FONTE DE COMPRA | K14: SD | M14: RC | O14: AF | Q14: CONTRAPARTIDA | S14: ENTREGA | U14: COMPLEMENTO
B16: 15 | C16: POLTRONA DE HIDRATACAO RECLINAVEL HOSPITALAR | E16: 1000 | G16: =B16*E16 -> 15000 | I16: HUMANITAS | K16: 4 | M16: 4 | O16: 4 | Q16: 3 | S16: 3 | U16: Bloco 1 - mobiliários e equip. prioritários (Ofício DGOC 111988/2025)
B17: 8 | C17: MESA EM FORMICA DE CABECEIRA | E17: 940 | G17: =B17*E17 -> 7520 | I17: HUMANITAS | K17: 4 | M17: 4 | O17: 4 | Q17: 3 | S17: 3
B18: 19 | C18: BANQUETA ALTA COM ENCOSTO | E18: 165 | G18: =B18*E18 -> 3135 | I18: HUMANITAS | K18: 4 | M18: 4 | O18: 4 | Q18: 3 | S18: 3
B19: 37 | C19: ESCADA C/ 02 DEGRAUS | E19: 215.5 | G19: =B19*E19 -> 7973.5 | I19: HUMANITAS | K19: 4 | M19: 4 | O19: 4 | Q19: 3 | S19: 3
B20: 18 | C20: MACA FIXA PARA MASSAGEM | E20: 706.67 | G20: =B20*E20 -> 12720.06 | I20: HUMANITAS | K20: 4 | M20: 4 | O20: 4 | Q20: 3 | S20: 3
B21: 1 | C21: ARMARIO ROUPEIRO COM 12 PORTAS | E21: 1698 | G21: =B21*E21 -> 1698 | I21: HUMANITAS | K21: 4 | M21: 4 | O21: 4 | Q21: 3 | S21: 3
B22: 8 | C22: ARMARIO TIPO ROUPEIRO COM 8 PORTAS | E22: 1994 | G22: =B22*E22 -> 15952 | I22: HUMANITAS | K22: 4 | M22: 4 | O22: 4 | Q22: 3 | S22: 3
B23: 5 | C23: ESTANTE DE ACO C/ 06 PRATELEIRAS | E23: 480 | G23: =B23*E23 -> 2400 | I23: HUMANITAS | K23: 4 | M23: 4 | O23: 4 | Q23: 3 | S23: 3
B24: 29 | C24: CADEIRA FIXA | E24: 170 | G24: =B24*E24 -> 4930 | I24: HUMANITAS | K24: 4 | M24: 4 | O24: 4 | Q24: 3 | S24: 3
B25: 38 | C25: CADEIRA GIRATORIA | E25: 646 | G25: =B25*E25 -> 24548 | I25: HUMANITAS | K25: 4 | M25: 4 | O25: 4 | Q25: 3 | S25: 3
B26: 11 | C26: CADEIRA DE RODAS ADULTO | E26: 683.2 | G26: =B26*E26 -> 7515.2 | I26: HUMANITAS | K26: 4 | M26: 4 | O26: 4 | Q26: 3 | S26: 3
B27: 1 | C27: CADEIRA DE RODAS OBESO | E27: 1990 | G27: =B27*E27 -> 1990 | I27: HUMANITAS | K27: 4 | M27: 4 | O27: 4 | Q27: 3 | S27: 3
B28: 1 | C28: MACA OBESO | E28: 1255 | G28: =B28*E28 -> 1255 | I28: HUMANITAS | K28: 4 | M28: 4 | O28: 4 | Q28: 3 | S28: 3
... B35: 8 | C35: ESFIGMOMANOMETRO ADULTO | E35: 99 | G35: =B35*E35 -> 792 | I35: HUMANITAS | K35: 4 | M35: 4 | O35: 4 | Q35: 3 | S35: 3
B36: 16 | C36: AFASTADOR FARABEUF 1,5X15 CM | E36: 17.6 | G36: =B36*E36 -> 281.6 | I36: HUMANITAS | K36: 4 | M36: 4 | O36: 4 | Q36: 3 | S36: 3 | U36: Bloco 2-instrumental, ventilatório e apoio CME (Ofício DGOC 21322/2026)
B37: 40 | C37: AMBU MÍNIMO 1600 ML | E37: 203.9672 | G37: =B37*E37 -> 8158.688 | I37: HUMANITAS | K37: 4 | M37: 4 | O37: 4 | Q37: 3 | S37: 3
B38: 22 | C38: BALDE 23 X 18 CM 5000ML | E38: 461 | G38: =B38*E38 -> 10142 | I38: HUMANITAS | K38: 4 | M38: 4 | O38: 4 | Q38: 3 | S38: 3
B39: 28 | C39: BANDEJA DE INOX RETANGULAR 42X30X02 CM | E39: 192.2 | G39: =B39*E39 -> 5381.6 | I39: HUMANITAS | K39: 4 | M39: 4 | O39: 4 | Q39: 3 | S39: 3
B40: 88 | C40: CABO DE BISTURI Nº: 3 | E40: 9.4 | G40: =B40*E40 -> 827.2 | I40: HUMANITAS | K40: 4 | M40: 4 | O40: 4 | Q40: 3 | S40: 3
B41: 4 | C41: CAIXA ORGANIZADORA 180L | E41: =G41/B41 -> 245.4 | G41: 981.6 | I41: HUMANITAS | K41: 4 | M41: 4 | O41: 4 | Q41: 3 | S41: 3
B42: 30 | C42: CIRCUITO DIXTAL | E42: 418.99 | G42: =B42*E42 -> 12569.7 | I42: HUMANITAS | K42: 4 | M42: 4 | O42: 4 | Q42: 3 | S42: 3
B43: 30 | C43: CIRCUITO TRANSPORTE | E43: 254.91 | G43: =B43*E43 -> 7647.3 | I43: HUMANITAS | K43: 4 | M43: 4 | O43: 4 | Q43: 3 | S43: 3
B44: 31 | C44: COMADRE 40 X 30 CM TIPO PA 3500ML | E44: 227.64 | G44: =B44*E44 -> 7056.84 | I44: HUMANITAS | K44: 4 | M44: 4 | O44: 4 | Q44: 3 | S44: 3
B45: 160 | C45: CUBA RIM | E45: 60.3 | G45: =B45*E45 -> 9648 | I45: HUMANITAS | K45: 4 | M45: 4 | O45: 4 | Q45: 3 | S45: 3
B46: 8 | C46: CUPULA (BACIA PARA ASSEPSIA) | E46: 16.2 | G46: =B46*E46 -> 129.6 | I46: HUMANITAS | K46: 4 | M46: 4 | O46: 4 | Q46: 3 | S46: 3
B47: 23 | C47: JARRO DE INOX 2 LITROS | E47: 77.32 | G47: =B47*E47 -> 1778.36 | I47: HUMANITAS | K47: 4 | M47: 4 | O47: 4 | Q47: 3 | S47: 3
B48: 50 | C48: KIT DE RETIRADA DE PONTOS | E48: 189.8 | G48: =B48*E48 -> 9490 | I48: HUMANITAS | K48: 4 | M48: 4 | O48: 4 | Q48: 3 | S48: 3
B49: 30 | C49: MÁSCARA DE VNI (VENTILAÇÃO NÃO INVASIVA) | E49: 84.7106 | G49: =B49*E49 -> 2541.318 | I49: HUMANITAS | K49: 4 | M49: 4 | O49: 4 | Q49: 3 | S49: 3
B50: 31 | C50: PAPAGAIO 26X15 CM 1000 ML | E50: 130.95 | G50: =B50*E50 -> 4059.45 | I50: HUMANITAS | K50: 4 | M50: 4 | O50: 4 | Q50: 3 | S50: 3
B51: 8 | C51: PINÇA ADSON DENTE DE RATO 12 CM | E51: 15.33 | G51: =B51*E51 -> 122.64 | I51: HUMANITAS | K51: 4 | M51: 4 | O51: 4 | Q51: 3 | S51: 3
B52: 8 | C52: PINÇA ADSON SERRILHADA | E52: 17.4 | G52: =B52*E52 -> 139.2 | I52: HUMANITAS | K52: 4 | M52: 4 | O52: 4 | Q52: 3 | S52: 3
B53: 8 | C53: PINÇA ANATÔMICA SERRILHADA 16 CM | E53: 17.7 | G53: =B53*E53 -> 141.6 | I53: HUMANITAS | K53: 4 | M53: 4 | O53: 4 | Q53: 3 | S53: 3
... B63: 88 | C63: TESOURA MAYO RETA 15 CM | E63: 55.41 | G63: =B63*E63 -> 4876.08 | I63: HUMANITAS | K63: 4 | M63: 4 | O63: 4 | Q63: 3 | S63: 3
B64: 100 | C64: CAPA PARA COLCHÃO HOSPITALAR EM COURVIM AZUL | E64: 39 | G64: =B64*E64 -> 3900 | I64: HUMANITAS | K64: 4 | M64: 4 | O64: 4 | Q64: 3 | S64: 3 | U64: Bloco 3-hotelaria (Ofício DGOC 21322/2026)
B65: 4 | C65: CAPA DE COLCHÃO HOSPITALAR | E65: 43 | G65: =B65*E65 -> 172 | I65: HUMANITAS | K65: 4 | M65: 4 | O65: 4 | Q65: 3 | S65: 3
B66: 2 | C66: COLCHÃO DE MACA HOSPITALAR REVESTIDO | E66: 110 | G66: =B66*E66 -> 220 | I66: HUMANITAS | K66: 4 | M66: 4 | O66: 4 | Q66: 3 | S66: 3
B67: 30 | C67: COLCHÃO DE CAMA HOSPITALAR AZUL ROYAL D 28 | E67: 320 | G67: =B67*E67 -> 9600 | I67: HUMANITAS | K67: 4 | M67: 4 | O67: 4 | Q67: 3 | S67: 3
B68: 10 | C68: COLCHÃO DE CAMA 1,80X0,78X0,12 - CONFORTO MÉDICO | E68: 230 | G68: =B68*E68 -> 2300 | I68: HUMANITAS | K68: 4 | M68: 4 | O68: 4 | Q68: 3 | S68: 3
B69: 1 | C69: AUTOCLAVE HORIZONTAL DE MESA 42 L | E69: 8502.3 | G69: =B69*E69 -> 8502.3 | I69: HUMANITAS | K69: 4 | M69: 4 | O69: 4 | Q69: 3 | S69: 2 | U69: Bloco 4 - engenharia clínica (Ofício DGOC 26795/2026)
B70: 10 | C70: BALANCA ANTROPOMETRICA DIGITAL PARA ATÉ 200 KG | E70: 1598 | G70: =B70*E70 -> 15980 | I70: HUMANITAS | Q70: 3 | S70: 3
B71: 1 | C71: BALANCA DE PLATAFORMA PARA 300 KG X 50 G | E71: 2500 | G71: =B71*E71 -> 2500 | I71: HUMANITAS | K71: 4 | M71: 4 | O71: 4 | Q71: 3 | S71: 3
B72: 3 | C72: CAMARA DE CONSERVACAO 280 L | E72: =60184.8/3 -> 20061.6 | G72: 60184.8 | I72: HUMANITAS | K72: 4 | M72: 4 | O72: 4 | Q72: 3 | S72: 2
B73: 1 | C73: CENTRÍFUGA | E73: 11488.8 | G73: =B73*E73 -> 11488.8 | I73: HUMANITAS | K73: 4 | M73: 4 | O73: 4 | Q73: 3 | S73: 3
B74: 10 | C74: TERMOHIGROMETRO DIGITAL | E74: 86.6 | G74: =B74*E74 -> 866 | I74: HUMANITAS | Q74: 3 | S74: 2
B75: 2 | C75: SERRA DE GESSO ELETRICA 220 VOLTS | E75: 1743.245 | G75: =B75*E75 -> 3486.49 | I75: HUMANITAS | Q75: 3 | S75: 3
B76: 61 | C76: LONGARINA DE 03 LUGARES, ESTRUTURA DE AÇO CARBONO (Compra conjunta - DAPRIS e DASS) | E76: 3573 | G76: =B76*E76 -> 217953 | I76: HUMANITAS | K76: 4 | M76: 4 | O76: 4 | Q76: 3 | S76: 2 | U76: Bloco 5 - mobiliários em geral (Ofício DGOC 24977/2026)
B77: 4 | C77: POLTRONA (Compra conjunta - DAPRIS e DASS) | E77: 1733 | G77: =B77*E77 -> 6932 | I77: HUMANITAS | K77: 4 | M77: 4 | O77: 4 | Q77: 3 | S77: 2
B78: 3 | C78: POLTRONA OBESO (Compra conjunta - DAPRIS e DASS) | E78: 1920 | G78: =B78*E78 -> 5760 | I78: HUMANITAS | K78: 4 | M78: 4 | O78: 4 | Q78: 3 | S78: 2
B79: 4 | C79: ARMÁRIO DE AÇO | E79: =G79/B79 -> 809 | G79: 3236 | I79: HUMANITAS | K79: 4 | M79: 4 | O79: 4 | Q79: 3 | S79: 2 | U79: Bloco 5 - mobiliários em geral (Ofício DGOC 34322/2026) | V79: entregue 1 UN
B80: 1 | C80: CADEIRA CAIXA ALTA - SECRETÁRIA EXECUTIVA | E80: 449 | G80: 449 | I80: HUMANITAS | K80: 4 | M80: 4 | O80: 4 | Q80: 3 | S80: 3
B81: 2 | C81: ESCADA 3 DEGRAUS ANTIDERRAPANTE | E81: =G81/B81 -> 357 | G81: 714 | I81: HUMANITAS | Q81: 3 | S81: 1
B82: 2 | C82: BANCO GIRATÓRIO | E82: =G82/B82 -> 269 | G82: 538 | I82: HUMANITAS | K82: 4 | M82: 4 | O82: 4 | Q82: 3 | S82: 3
B83: 2 | C83: ARMÁRIO ALTO PARA QUÍMICOS | E83: =G83/B83 -> 5858 | G83: 11716 | I83: HUMANITAS | K83: 4 | M83: 4 | O83: 4 | Q83: 3 | S83: 1
B84: 24 | C84: MESA LATERAL DE APOIO | E84: =G84/B84 -> 831.67667 | G84: 19960.24 | I84: HUMANITAS | K84: 4 | M84: 4 | O84: 4 | Q84: 3 | S84: 1
B85: 18 | C85: MESA AUXILIAR INOX | E85: =G85/B85 -> 540 | G85: 9720 | I85: HUMANITAS | K85: 4 | M85: 4 | O85: 4 | Q85: 3 | S85: 1
B86: 10 | C86: MESA DE REFEIÇÃO INOX | E86: =G86/B86 -> 506.492 | G86: 5064.92 | I86: HUMANITAS | K86: 4 | M86: 4 | O86: 4 | Q86: 3 | S86: 1
B87: 21 | C87: BIOMBO | E87: =G87/B87 -> 577.99905 | G87: 12137.98 | I87: HUMANITAS | K87: 4 | M87: 4 | O87: 4 | Q87: 3 | S87: 1
B88: 2 | C88: CARRO DE MEDICAÇÃO | E88: =G88/2 -> 2106.46 | G88: 4212.92 | I88: HUMANITAS | K88: 4 | M88: 4 | O88: 4 | Q88: 3 | S88: 1
B89: 46 | C89: SUPORTE DE SORO MÓVEL | E89: =G89/B89 -> 351 | G89: 16146 | I89: HUMANITAS | K89: 4 | M89: 4 | O89: 4 | Q89: 3 | S89: 1
B90: 15 | C90: CORTINA COM TRILHO P/ DIVISÓRIA DE LEITO | E90: =G90/B90 -> 541.55867 | G90: 8123.38 | I90: HUMANITAS | K90: 4 | M90: 4 | O90: 4 | Q90: 3 | S90: 1
B91: 1 | C91: MACA PARA BANHO | E91: 7150 | G91: 7150 | I91: HUMANITAS | K91: 4 | M91: 4 | O91: 4 | Q91: 3 | S91: 1
B92: 8 | C92: CADEIRA PARA BANHO HIGIÉNICA DOBRÁVEL ATÉ 100KG | E92: =G92/B92 -> 275.65 | G92: 2205.2 | I92: HUMANITAS | K92: 4 | M92: 4 | O92: 4 | Q92: 3 | S92: 1
B93: 3 | C93: CARRINHO AUXILIAR EM AÇO INOX COM CESTOS | E93: =G93/B93 -> 1786.0833 | G93: 5358.25 | I93: HUMANITAS | K93: 4 | M93: 4 | O93: 4 | Q93: 3 | S93: 1
B94: 5 | C94: CAIXA TÉRMICA 5 L | E94: =G94/B94 -> 225 | G94: 1125 | I94: HUMANITAS | K94: 4 | M94: 4 | O94: 4 | Q94: 3 | S94: 3
B95: 4 | C95: PURIFICADOR DE ÁGUA | E95: 600 | G95: =B95*E95 -> 2400 | I95: HUMANITAS | K95: 4 | M95: 4 | O95: 4 | Q95: 3 | S95: 3 | U95: Bloco 6 - utensílios copa, cozinha e alim. (Ofício DGOC 28470/2026)
B96: 2 | C96: FRIGOBAR | E96: 1202.6 | G96: =B96*E96 -> 2405.2 | I96: HUMANITAS | K96: 4 | M96: 4 | O96: 4 | Q96: 3 | S96: 3
B97: 1 | C97: MESA EM AÇO INOX 304 | E97: 1850 | G97: =B97*E97 -> 1850 | I97: HUMANITAS | K97: 4 | M97: 4 | O97: 4 | Q97: 3 | S97: 2
B98: 2 | C98: CARRO AQUECIDO PARA TRANSPORTE DE BANDEJAS | E98: 8898 | G98: =B98*E98 -> 17796 | I98: HUMANITAS | K98: 4 | M98: 4 | O98: 4 | Q98: 3 | S98: 2
B99: 3 | C99: MICRO-ONDAS 28 LITROS | E99: 700 | G99: =B99*E99 -> 2100 | I99: HUMANITAS | K99: 4 | M99: 4 | O99: 4 | Q99: 3 | S99: 3
B100: 1 | C100: CAFETEIRA ELETRICA INDUSTRIAL - CAPACIDADE DE 20 L | E100: 3043 | G100: =B100*E100 -> 3043 | I100: HUMANITAS | K100: 4 | M100: 4 | O100: 4 | Q100: 3 | S100: 2
B101: 4 | C101: CARRO FUNCIONAL | K101: 4 | M101: 4 | O101: 4 | Q101: 3 | S101: 1 | U101: Bloco 7-limpeza (Ofício DGOC 41081/2026)
B102: 2 | C102: CARRO CUBA COMUM | E102: =5028/2 -> 2514 | G102: =B102*E102 -> 5028 | K102: 4 | M102: 4 | O102: 4 | Q102: 3 | S102: 1
B103: 2 | C103: CARRO CUBA INFECTANTE | E103: 2514 | G103: =B103*E103 -> 5028 | K103: 4 | M103: 4 | O103: 4 | Q103: 3 | S103: 1
B104: 4 | C104: CARRO FUNCIONAL | E104: =2693.6/B104 -> 673.4 | G104: =B104*E104 -> 2693.6 | K104: 4 | M104: 4 | O104: 4 | Q104: 3 | S104: 1
B105: 10 | C105: CESTO FUNCIONAL ORGANIZADO DE PRODUTOS DE LIMPEZA | E105: 40.9 | G105: =B105*E105 -> 409 | K105: 4 | M105: 4 | O105: 4 | Q105: 3 | S105: 1
B106: 4 | C106: ENCERADEIRA PARA LAVAR PISOS. MOTOR ¾ HP, 110 /220V - BIVOLT, DIÂM. DA ESCOVA: 35 CM, 1 SUPORTE PARA DISCO, 1 ESCOVA PARA LAVAR. PESO LÍQUIDO: 22,00 KG. | E106: =10251.6/B106 -> 2562.9 | G106: =B106*E106 -> 10251.6 | K106: 4 | M106: 4 | O106: 4 | Q106: 3 | S106: 1
B107: 10 | C107: KIT MOP SPRAY PROFISSIONAL | E107: 224.54 | G107: =B107*E107 -> 2245.4 | K107: 4 | M107: 4 | O107: 4 | Q107: 3 | S107: 1
B108: 4 | C108: KIT PLUS PARA LIMPEZA DE VIDROS | E108: =1464/B108 -> 366 | G108: =B108*E108 -> 1464 | K108: 4 | M108: 4 | O108: 4 | Q108: 3 | S108: 1
B109: 18 | C109: LIXEIRA BRANCA 50L | E109: =1798.2/B109 -> 99.9 | G109: =B109*E109 -> 1798.2 | K109: 4 | M109: 4 | O109: 4 | Q109: 3 | S109: 1
B110: 43 | C110: LIXEIRA PRETA 50L | E110: =4867.17/B110 -> 113.19 | G110: =B110*E110 -> 4867.17 | K110: 4 | M110: 4 | O110: 4 | Q110: 3 | S110: 1
B111: 4 | C111: LIXEIRA AMARELA 240L | E111: =1319.6/B111 -> 329.9 | G111: =B111*E111 -> 1319.6 | K111: 4 | M111: 4 | O111: 4 | Q111: 3 | S111: 1
B112: 8 | C112: LIXEIRA AZUL 240L | E112: =2639.2/B112 -> 329.9 | G112: =B112*E112 -> 2639.2 | K112: 4 | M112: 4 | O112: 4 | Q112: 3 | S112: 1
B113: 14 | C113: LIXEIRA AZUL 25L | E113: =950.46/B113 -> 67.89 | G113: =B113*E113 -> 950.46 | K113: 4 | M113: 4 | O113: 4 | Q113: 3 | S113: 1
B114: 3 | C114: LIXEIRA AZUL 50L | E114: =215.1/B114 -> 71.7 | G114: =B114*E114 -> 215.1 | K114: 4 | M114: 4 | O114: 4 | Q114: 3 | S114: 1
B115: 8 | C115: LIXEIRA BRANCA 240L | E115: =2639.2/B115 -> 329.9 | G115: =B115*E115 -> 2639.2 | K115: 4 | M115: 4 | O115: 4 | Q115: 3 | S115: 1
B116: 4 | C116: LIXEIRA BRANCA 25L | E116: =215.6/B116 -> 53.9 | G116: =B116*E116 -> 215.6 | K116: 4 | M116: 4 | O116: 4 | Q116: 3 | S116: 1
B117: 8 | C117: LIXEIRA PRETA 240L | E117: =2639.2/B117 -> 329.9 | G117: =B117*E117 -> 2639.2 | K117: 4 | M117: 4 | O117: 4 | Q117: 3 | S117: 1
B118: 12 | C118: LIXEIRA PRETA 25L | E118: =939.72/B118 -> 78.31 | G118: =B118*E118 -> 939.72 | K118: 4 | M118: 4 | O118: 4 | Q118: 3 | S118: 1
B119: 20 | C119: MOP PÓ MICROFIBRA. MEDIDAS 47,0 X 14,0 X 1,3 CM | E119: =1946.6/B119 -> 97.33 | G119: =B119*E119 -> 1946.6 | K119: 4 | M119: 4 | O119: 4 | Q119: 3 | S119: 1
B120: 100 | C120: REFIL MOP ÚMIDO | E120: =6500/100 -> 65 | G120: =B120*E120 -> 6500 | K120: 4 | M120: 4 | O120: 4 | Q120: 3 | S120: 1
B121: 10 | C121: RODO 45 CM "DRY" C/ ENCAIXE SISTEMA EURO. CÓDIGO RN45AZ | E121: 25.9 | G121: =B121*E121 -> 259 | K121: 4 | M121: 4 | O121: 4 | Q121: 3 | S121: 1
...

Sheet HOSPITAL CLÍNICA SUL
B1: Centro Cirúrgico - Hospital Clínica Sul
B3: ESTIMATIVA DE ENTREGA: | K3: 46142 | M3: RESTAM : | O3: =K3-TODAY() -> -48 | Q3: DIAS
B5: OBJETIVO
B6: Acompanhar, monitorar e controlar as etapas da execução da obra, bem como a aquisição de equipamentos necessários para seu pleno funcionamento. Problema: Risco de descompasso entre o término das obras e a aquisição de materiais e equipamentos. Solução: Implantar ferramenta única para organizar e acompanhar as aquisições por unidade, conforme o cronograma das obras. Benefício: Garantir início de funcionamento sem atrasos, com melhor planejamento e integração entre as áreas. | I6: Expediente 75449/2025 - PLANO DE TRABALHO PARA OPERACIONALIZAÇÃO DO CENTRO CIRURGICO E CME (itens a serem adquiridos por aditivo no contrato de gestão Microrregião Sul, se aprovado o plano) | Q6: LEGENDA | U6: 12/02: Plano de Trabalho seguiu para DPOS - FMS informar a dotação orçamentária referente ao aditamento contratual. Início da operacionalização previsto para maio/2026, após o término das obras (abril/2026). Valores referenciados de custeio 1º mês - Maio/26 - R$ 403.399,00; 2º mês - Jun/26 - R$ 518.656,00; 3º mês - Jul/2026 a Dez/28 - Mensal: R$ 922.056,00, totalizando: R$ 27.661.680,00. Valor total de custeio: R$ 28.583.735,00. Valor total de investimento (máquinas e equipamentos): R$ 7.689.866,96,00.
Q8: 1 | S8: 1. Atenção
Q9: 2 | S9: 2. Em andamento
Q10: 3 | S10: 3. Finalizado
Q11: 4 | S11: 4. Não Necessita
B14: QTDE | C14: ITENS | E14: Valor Unitário (Estimado) | G14: Valor Total (Estimado) | I14: FONTE DE COMPRA | K14: SD | M14: RC | O14: AF | Q14: CONTRAPARTIDA | S14: ENTREGA | U14: COMPLEMENTO
B16: 30 | C16: AMBÚ ADULTO | E16: 315 | G16: =B16*E16 -> 9450 | I16: ADITAMENTO | K16: 4 | M16: 4 | O16: 4 | Q16: 1 | S16: 1
B17: 3 | C17: APARELHO DE BISTURI ELETRICO PARA CIRURGIA ALTA COMPLEXIDADE | E17: 56000 | G17: =B17*E17 -> 168000 | I17: ADITAMENTO | K17: 4 | M17: 4 | O17: 4 | Q17: 1 | S17: 1
B18: 4 | C18: APARELHO DE TRICOTOMIA | E18: 480 | G18: =B18*E18 -> 1920 | I18: ADITAMENTO | K18: 4 | M18: 4 | O18: 4 | Q18: 1 | S18: 1
B19: 1 | C19: APARELHO DE ULTRASSONOGRAFIA | E19: 125000 | G19: =B19*E19 -> 125000 | I19: ADITAMENTO | K19: 4 | M19: 4 | O19: 4 | Q19: 1 | S19: 1
B20: 2 | C20: AQUECEDOR DE CONTRASTE E SOLUÇÕES INJETÁVEIS | E20: 15700 | G20: =B20*E20 -> 31400 | I20: ADITAMENTO | K20: 4 | M20: 4 | O20: 4 | Q20: 1 | S20: 1
B21: 5 | C21: ASPIRADOR PORTÁTIL | E21: 7820 | G21: =B21*E21 -> 39100 | I21: ADITAMENTO | K21: 4 | M21: 4 | O21: 4 | Q21: 1 | S21: 1
B22: 4 | C22: AVENTAL DE CHUMBO | E22: 1980 | G22: =B22*E22 -> 7920 | I22: ADITAMENTO | K22: 4 | M22: 4 | O22: 4 | Q22: 1 | S22: 1
B23: 6 | C23: BALDE CHUTE INOX 30LITROS | E23: 780 | G23: =B23*E23 -> 4680 | I23: ADITAMENTO | K23: 4 | M23: 4 | O23: 4 | Q23: 1 | S23: 1
B24: 2 | C24: BEBEDOURO | E24: 1315 | G24: =B24*E24 -> 2630 | I24: ADITAMENTO | K24: 4 | M24: 4 | O24: 4 | Q24: 1 | S24: 1
B25: 10 | C25: BUGIE ESTILETE DE ENTUBAÇÃO | E25: 65 | G25: =B25*E25 -> 650 | I25: ADITAMENTO | K25: 4 | M25: 4 | O25: 4 | Q25: 1 | S25: 1
B26: 4 | C26: CAIXA KITS DE CIRURGIA DE VIDEO ( CIRURGIAS COLECISTECTOMIA, APENDICECTOMIA) | E26: 113875.39 | G26: =B26*E26 -> 455501.56 | I26: ADITAMENTO | K26: 4 | M26: 4 | O26: 4 | Q26: 1 | S26: 1
B27: 1 | C27: CARRINHO DE EMERGENCIA | E27: 3950 | G27: =B27*E27 -> 3950 | I27: ADITAMENTO | K27: 4 | M27: 4 | O27: 4 | Q27: 1 | S27: 1
... B182: 1 | C182: RESPIRADOR DE TRANSPORTE | E182: 56000 | G182: =B182*E182 -> 56000 | I182: ADITAMENTO | K182: 4 | M182: 4 | O182: 4 | Q182: 1 | S182: 1
B183: 1 | C183: SISTEMA DE EXAUSTÃO COM COIFA ÁREA DESINFECÇÃO | E183: - | I183: ADITAMENTO | K183: 4 | M183: 4 | O183: 4 | Q183: 1 | S183: 1
B184: 2 | C184: SUPORTE DE DESCARPACK 13 L | E184: 85 | G184: =B184*E184 -> 170 | I184: ADITAMENTO | K184: 4 | M184: 4 | O184: 4 | Q184: 1 | S184: 1
B185: 2 | C185: SUPORTE DE HAMPER INOX COM RODÍZIO | E185: 390 | G185: =B185*E185 -> 780 | I185: ADITAMENTO | K185: 4 | M185: 4 | O185: 4 | Q185: 1 | S185: 1
B186: 4 | C186: SUPORTE DE SORO COM RODÍZIO | E186: 454 | G186: =B186*E186 -> 1816 | I186: ADITAMENTO | K186: 4 | M186: 4 | O186: 4 | Q186: 1 | S186: 1
B187: 4 | C187: SUPORTE DE SORO SEM RODÍZIO | E187: 380 | G187: =B187*E187 -> 1520 | I187: ADITAMENTO | K187: 4 | M187: 4 | O187: 4 | Q187: 1 | S187: 1
B188: 2 | C188: SUPORTE PARA CILINDRO DE CO2 | E188: 640 | G188: =B188*E188 -> 1280 | I188: ADITAMENTO | K188: 4 | M188: 4 | O188: 4 | Q188: 1 | S188: 1
B189: 0 | C189: TORRE DE BRONCOSCOPIA + BRONCOSCÓPIO | E189: 499500 | G189: =B189*E189 -> 0 | I189: ADITAMENTO | K189: 4 | M189: 4 | O189: 4 | Q189: 1 | S189: 1
B190: 0 | C190: TORRE DE VIDEO-ENDOSCOPIA COMPLETA - ENDOSCOPIA | E190: 390742 | G190: =B190*E190 -> 0 | I190: ADITAMENTO | K190: 4 | M190: 4 | O190: 4 | Q190: 1 | S190: 1
B191: 0 | C191: TORRE DE VIDEO-ENDOSCOPIA COMPLETA- COLONOSCOPIA | E191: 399500 | G191: =B191*E191 -> 0 | I191: ADITAMENTO | K191: 4 | M191: 4 | O191: 4 | Q191: 1 | S191: 1
B192: 6 | C192: VACUÔMETRO | E192: 210 | G192: =B192*E192 -> 1260 | I192: ADITAMENTO | K192: 4 | M192: 4 | O192: 4 | Q192: 1 | S192: 1
B193: 2 | C193: VÁLVULA REGULADORA DE AR MEDICINAL | E193: 280 | G193: =B193*E193 -> 560 | I193: ADITAMENTO | K193: 4 | M193: 4 | O193: 4 | Q193: 1 | S193: 1
B194: 2 | C194: VÁLVULA REGULADORA DE O2 | E194: 280 | G194: =B194*E194 -> 560 | I194: ADITAMENTO | K194: 4 | M194: 4 | O194: 4 | Q194: 1 | S194: 1
B195: 2 | C195: VÁLVULA REGULADORA DE ÓXIDO NITROSO | E195: 280 | G195: =B195*E195 -> 560 | I195: ADITAMENTO | K195: 4 | M195: 4 | O195: 4 | Q195: 1 | S195: 1
C197: TOTAL | G197: =SUM(G16:G195) -> 7689867
E199: HUMANITAS | G199: =SUMIF(I16:I195,E199,G16:G195) -> 0
E201: PREFEITURA | G201: =SUMIF(I16:I195,E201,G16:G195) -> 0
C202: Total | K202: =SUM(K203:K206) -> 180 | M202: =SUM(M203:M206) -> 180 | O202: =SUM(O203:O206) -> 180 | Q202: =SUM(Q203:Q206) -> 180 | S202: =SUM(S203:S206) -> 180
C203: Atenção | K203: =COUNTIF(K16:K195,Q8) -> 0 | M203: =COUNTIF(M16:M195,Q8) -> 0 | O203: =COUNTIF(O16:O195,Q8) -> 0 | Q203: =COUNTIF(Q16:Q195,Q8) -> 180 | S203: =COUNTIF(S16:S195,Q8) -> 180
C204: Em andamento | K204: =COUNTIF(K16:K195,Q9) -> 0 | M204: =COUNTIF(M16:M195,Q9) -> 0 | O204: =COUNTIF(O16:O195,Q9) -> 0 | Q204: =COUNTIF(Q16:Q195,Q9) -> 0 | S204: =COUNTIF(S16:S195,Q9) -> 0
C205: Finalizado | K205: =COUNTIF(H16:K195,Q10) -> 0 | M205: =COUNTIF(M16:M195,Q10) -> 0 | O205: =COUNTIF(O16:O195,Q10) -> 0 | Q205: =COUNTIF(Q16:Q195,Q10) -> 0 | S205: =COUNTIF(S16:S195,Q10) -> 0
C206: Não Necessita | K206: =COUNTIF(K16:K195,Q11) -> 180 | M206: =COUNTIF(M16:M195,Q11) -> 180 | O206: =COUNTIF(O16:O195,Q11) -> 180 | Q206: =COUNTIF(Q16:Q195,Q11) -> 0 | S206: =COUNTIF(S16:S195,Q11) -> 0
E208: ADITAMENTO | G208: =SUMIF(I16:I195,E208,G16:G195) -> 7689867 | K208: SD | M208: RC | O208: AF | Q208: CONTRAPARTIDA | S208: ENTREGA
C210: FINALIZADA | K210: =K205/K202 -> 0 | M210: =M205/M202 -> 0 | O210: =O205/O202 -> 0 | Q210: =Q205/Q202 -> 0 | S210: =S205/S202 -> 0
C212: EM ANDAMENTO | K212: =K204/K202 -> 0 | M212: =M204/M202 -> 0 | O212: =O204/O202 -> 0 | Q212: =Q204/Q202 -> 0 | S212: =S204/S202 -> 0
C214: ATENÇÃO | K214: =K203/K202 -> 0 | M214: =M203/M202 -> 0 | O214: =O203/O202 -> 0 | Q214: =Q203/Q202 -> 1 | S214: =S203/S202 -> 1
G217: =G199+G201 -> 0

Sheet RESUMO - FONTES DE PGTO
B1: RESUMO - FONTES DE PAGAMENTO
B3: UBS CAJURU | E3: CER III | H3: UBS VILA INDUSTRIAL | K3: HOSPITAL CLÍNICA SUL | N3: NOVO PS ADULTO - HM
B5: PREFEITURA | C5: ='UBS CAJURU'!G85 -> 0 | E5: PREFEITURA | F5: ='CER III'!G266 -> 1340765.4 | H5: PREFEITURA | I5: ='UBS VL INDUSTRIAL'!G64 -> 0 | K5: PREFEITURA | L5: ='HOSPITAL CLÍNICA SUL'!G201 -> 0 | N5: PREFEITURA | O5: ='HOSPITAL DE RETAGUARDA'!G163 -> 0
B7: HUMANITAS | C7: ='UBS CAJURU'!G83 -> 533443.59 | E7: HUMANITAS | F7: ='CER III'!G264 -> 0 | H7: HUMANITAS | I7: ='UBS VL INDUSTRIAL'!G62 -> 500370.51 | K7: HUMANITAS | L7: ='HOSPITAL CLÍNICA SUL'!G199 -> 0 | N7: HUMANITAS | O7: ='HOSPITAL DE RETAGUARDA'!G161 -> 1140107.3
B9: ADITAMENTO | C9: ='UBS CAJURU'!G92 -> 0 | E9: ADITAMENTO | F9: ='CER III'!G273 -> 0 | H9: ADITAMENTO | I9: ='UBS VL INDUSTRIAL'!G71 -> 0 | K9: ADITAMENTO | L9: ='HOSPITAL CLÍNICA SUL'!G208 -> 7689867 | N9: ADITAMENTO | O9: ='HOSPITAL DE RETAGUARDA'!G170 -> 0
B11: TOTAL | C11: ='UBS CAJURU'!G81 -> 533443.59 | E11: TOTAL | F11: ='CER III'!G262 -> 1340765.4 | H11: TOTAL | I11: ='UBS VL INDUSTRIAL'!G60 -> 500370.51 | K11: TOTAL | L11: ='HOSPITAL CLÍNICA SUL'!G197 -> 7689867 | N11: TOTAL | O11: ='HOSPITAL DE RETAGUARDA'!G159 -> 1216161.9
B13: FONTE A DEFINIR | C13: =C11-C9-C7-C5 -> 0 | E13: FONTE A DEFINIR | F13: =F11-F9-F7-F5 -> 0 | H13: FONTE A DEFINIR | I13: =T11-T9-T7-T5 -> 0 | K13: FONTE A DEFINIR | L13: =L11-L5-L7-L9 -> 0 | N13: FONTE A DEFINIR | O13: =O11-O5-O7-O9 -> 76054.61
B17: UBS PARAÍSO DO SOL | E17: UBS JARDIM DA GRANJA | H17: UBS JARDIM SATÉLITE | K17: UBS VILA NAIR
B19: PREFEITURA | C19: ='UBS CAJURU'!G99 -> 0 | E19: PREFEITURA | F19: ='CER III'!G280 -> 0 | H19: PREFEITURA | I19: ='UBS VL INDUSTRIAL'!G78 -> 0 | K19: PREFEITURA | L19: ='HOSPITAL CLÍNICA SUL'!G215 -> 0
B21: HUMANITAS | C21: ='UBS P. DO SOL'!G21 -> 69145 | E21: HUMANITAS | F21: ='UBS JD GRANJA'!G20 -> 45145 | H21: HUMANITAS | I21: ='UBS JD SATÉLITE'!G20 -> 45145 | K21: HUMANITAS | L21: ='UBS VL NAIR'!G20 -> 26620
B23: ADITAMENTO | C23: ='UBS CAJURU'!G106 -> 0 | E23: ADITAMENTO | F23: ='CER III'!G287 -> 0 | H23: ADITAMENTO | I23: ='UBS VL INDUSTRIAL'!G85 -> 0 | K23: ADITAMENTO | L23: ='HOSPITAL CLÍNICA SUL'!G222 -> 0
B25: TOTAL | C25: ='UBS P. DO SOL'!G21 -> 69145 | E25: TOTAL | F25: ='UBS JD GRANJA'!G20 -> 45145 | H25: TOTAL | I25: ='UBS JD SATÉLITE'!G20 -> 45145 | K25: TOTAL | L25: ='UBS VL NAIR'!G20 -> 26620
B27: FONTE A DEFINIR | C27: =C25-C23-C21-C19 -> 0 | E27: FONTE A DEFINIR | F27: =F25-F23-F21-F19 -> 0 | H27: FONTE A DEFINIR | I27: =I25-I23-I21-I19 -> 0 | K27: FONTE A DEFINIR | L27: =L25-L19-L21-L23 -> 0
B30: TA SPDM para operacionalização da unidade | L30: =L25+I25+F25+C25+C11+I11 -> 1219869.1
L31: =529108+274316 -> 803424
B32: Falta projeto de mobiliário planejado (Pedro). Irá decidir se planejado ou não. | E32: =C7+I7+O7+C21+F21+I21+L21 -> 2359976.4 | H32: Será com mobiliários planejados. Aproximadamente R$ 200 mil. Não constante na lista. Mas dar andamento na aquisição dos equipamentos.
B34: Elaine deverá em contato com o DPSS para cotação e posterior envio para a Humanitas | H34: Elaine deverá em contato com o DPSS para cotação e posterior envio para a Humanitas
B36: Elaine poderá servir de apoio para a Humanitas | H36: Elaine poderá servir de apoio para a Humanitas

Sheet Planilha1
